<?xml version="1.0" encoding="UTF-8"?>

<!-- generated on 2025-12-01 22:22:37 by Eclipse SUMO GUI Version 1.24.0
<sumoConfiguration xmlns:xsi="http://www.w3.org/2001/XMLSchema-instance" xsi:noNamespaceSchemaLocation="http://sumo.dlr.de/xsd/sumoConfiguration.xsd">

    <input>
        <net-file value="rainbow.net.xml"/>
        <route-files value="rainbow.rou.xml"/>
        <additional-files value="map.poly.xml,rainbow.detectors.add.xml"/>
    </input>

    <time>
        <begin value="0"/>
        <end value="10800"/>
        <step-length value="1.0"/>
    </time>

    <processing>
        <time-to-teleport value="-1"/>
    </processing>

    <report>
        <no-step-log value="true"/>
    </report>

    <traci_server>
        <remote-port value="50626"/>
    </traci_server>

</sumoConfiguration>
-->

<detector xmlns:xsi="http://www.w3.org/2001/XMLSchema-instance" xsi:noNamespaceSchemaLocation="http://sumo.dlr.de/xsd/det_e2_file.xsd">
   <interval begin="0.00" end="120.00" id="e2_east_0" sampledSeconds="6.68" nVehEntered="6" nVehLeft="5" nVehSeen="6" meanSpeed="19.66" meanTimeLoss="0.02" meanOccupancy="1.29" maxOccupancy="25.00" meanMaxJamLengthInVehicles="0.00" meanMaxJamLengthInMeters="0.00" maxJamLengthInVehicles="0" maxJamLengthInMeters="0.00" jamLengthInVehiclesSum="0" jamLengthInMetersSum="0.00" meanHaltingDuration="0.00" maxHaltingDuration="0.00" haltingDurationSum="0.00" meanIntervalHaltingDuration="0.00" maxIntervalHaltingDuration="0.00" intervalHaltingDurationSum="0.00" startedHalts="0.00" meanVehicleNumber="0.11" maxVehicleNumber="1" />
   <interval begin="0.00" end="120.00" id="e2_east_1" sampledSeconds="3.72" nVehEntered="6" nVehLeft="6" nVehSeen="6" meanSpeed="19.30" meanTimeLoss="0.00" meanOccupancy="1.04" maxOccupancy="25.00" meanMaxJamLengthInVehicles="0.00" meanMaxJamLengthInMeters="0.00" maxJamLengthInVehicles="0" maxJamLengthInMeters="0.00" jamLengthInVehiclesSum="0" jamLengthInMetersSum="0.00" meanHaltingDuration="0.00" maxHaltingDuration="0.00" haltingDurationSum="0.00" meanIntervalHaltingDuration="0.00" maxIntervalHaltingDuration="0.00" intervalHaltingDurationSum="0.00" startedHalts="0.00" meanVehicleNumber="0.05" maxVehicleNumber="1" />
   <interval begin="0.00" end="120.00" id="e2_east_2" sampledSeconds="3.59" nVehEntered="5" nVehLeft="5" nVehSeen="5" meanSpeed="19.06" meanTimeLoss="0.01" meanOccupancy="0.00" maxOccupancy="0.00" meanMaxJamLengthInVehicles="0.00" meanMaxJamLengthInMeters="0.00" maxJamLengthInVehicles="0" maxJamLengthInMeters="0.00" jamLengthInVehiclesSum="0" jamLengthInMetersSum="0.00" meanHaltingDuration="0.00" maxHaltingDuration="0.00" haltingDurationSum="0.00" meanIntervalHaltingDuration="0.00" maxIntervalHaltingDuration="0.00" intervalHaltingDurationSum="0.00" startedHalts="0.00" meanVehicleNumber="0.04" maxVehicleNumber="1" />
   <interval begin="0.00" end="120.00" id="e2_east_3" sampledSeconds="0.00" nVehEntered="0" nVehLeft="0" nVehSeen="0" meanSpeed="-1.00" meanTimeLoss="-1.00" meanOccupancy="0.00" maxOccupancy="0.00" meanMaxJamLengthInVehicles="0.00" meanMaxJamLengthInMeters="0.00" maxJamLengthInVehicles="0" maxJamLengthInMeters="0.00" jamLengthInVehiclesSum="0" jamLengthInMetersSum="0.00" meanHaltingDuration="0.00" maxHaltingDuration="0.00" haltingDurationSum="0.00" meanIntervalHaltingDuration="0.00" maxIntervalHaltingDuration="0.00" intervalHaltingDurationSum="0.00" startedHalts="0.00" meanVehicleNumber="0.00" maxVehicleNumber="0" />
   <interval begin="0.00" end="120.00" id="e2_east_4" sampledSeconds="0.00" nVehEntered="0" nVehLeft="0" nVehSeen="0" meanSpeed="-1.00" meanTimeLoss="-1.00" meanOccupancy="0.00" maxOccupancy="0.00" meanMaxJamLengthInVehicles="0.00" meanMaxJamLengthInMeters="0.00" maxJamLengthInVehicles="0" maxJamLengthInMeters="0.00" jamLengthInVehiclesSum="0" jamLengthInMetersSum="0.00" meanHaltingDuration="0.00" maxHaltingDuration="0.00" haltingDurationSum="0.00" meanIntervalHaltingDuration="0.00" maxIntervalHaltingDuration="0.00" intervalHaltingDurationSum="0.00" startedHalts="0.00" meanVehicleNumber="0.00" maxVehicleNumber="0" />
   <interval begin="120.00" end="240.00" id="e2_east_0" sampledSeconds="5.47" nVehEntered="6" nVehLeft="7" nVehSeen="7" meanSpeed="19.18" meanTimeLoss="0.02" meanOccupancy="1.30" maxOccupancy="25.00" meanMaxJamLengthInVehicles="0.00" meanMaxJamLengthInMeters="0.00" maxJamLengthInVehicles="0" maxJamLengthInMeters="0.00" jamLengthInVehiclesSum="0" jamLengthInMetersSum="0.00" meanHaltingDuration="0.00" maxHaltingDuration="0.00" haltingDurationSum="0.00" meanIntervalHaltingDuration="0.00" maxIntervalHaltingDuration="0.00" intervalHaltingDurationSum="0.00" startedHalts="0.00" meanVehicleNumber="0.11" maxVehicleNumber="1" />
   <interval begin="120.00" end="240.00" id="e2_east_1" sampledSeconds="7.45" nVehEntered="8" nVehLeft="8" nVehSeen="8" meanSpeed="19.26" meanTimeLoss="0.02" meanOccupancy="0.94" maxOccupancy="25.00" meanMaxJamLengthInVehicles="0.00" meanMaxJamLengthInMeters="0.00" maxJamLengthInVehicles="0" maxJamLengthInMeters="0.00" jamLengthInVehiclesSum="0" jamLengthInMetersSum="0.00" meanHaltingDuration="0.00" maxHaltingDuration="0.00" haltingDurationSum="0.00" meanIntervalHaltingDuration="0.00" maxIntervalHaltingDuration="0.00" intervalHaltingDurationSum="0.00" startedHalts="0.00" meanVehicleNumber="0.09" maxVehicleNumber="1" />
   <interval begin="120.00" end="240.00" id="e2_east_2" sampledSeconds="4.22" nVehEntered="5" nVehLeft="5" nVehSeen="5" meanSpeed="19.00" meanTimeLoss="0.02" meanOccupancy="0.57" maxOccupancy="25.00" meanMaxJamLengthInVehicles="0.00" meanMaxJamLengthInMeters="0.00" maxJamLengthInVehicles="0" maxJamLengthInMeters="0.00" jamLengthInVehiclesSum="0" jamLengthInMetersSum="0.00" meanHaltingDuration="0.00" maxHaltingDuration="0.00" haltingDurationSum="0.00" meanIntervalHaltingDuration="0.00" maxIntervalHaltingDuration="0.00" intervalHaltingDurationSum="0.00" startedHalts="0.00" meanVehicleNumber="0.07" maxVehicleNumber="1" />
   <interval begin="120.00" end="240.00" id="e2_east_3" sampledSeconds="0.00" nVehEntered="0" nVehLeft="0" nVehSeen="0" meanSpeed="-1.00" meanTimeLoss="-1.00" meanOccupancy="0.00" maxOccupancy="0.00" meanMaxJamLengthInVehicles="0.00" meanMaxJamLengthInMeters="0.00" maxJamLengthInVehicles="0" maxJamLengthInMeters="0.00" jamLengthInVehiclesSum="0" jamLengthInMetersSum="0.00" meanHaltingDuration="0.00" maxHaltingDuration="0.00" haltingDurationSum="0.00" meanIntervalHaltingDuration="0.00" maxIntervalHaltingDuration="0.00" intervalHaltingDurationSum="0.00" startedHalts="0.00" meanVehicleNumber="0.00" maxVehicleNumber="0" />
   <interval begin="120.00" end="240.00" id="e2_east_4" sampledSeconds="0.00" nVehEntered="0" nVehLeft="0" nVehSeen="0" meanSpeed="-1.00" meanTimeLoss="-1.00" meanOccupancy="0.00" maxOccupancy="0.00" meanMaxJamLengthInVehicles="0.00" meanMaxJamLengthInMeters="0.00" maxJamLengthInVehicles="0" maxJamLengthInMeters="0.00" jamLengthInVehiclesSum="0" jamLengthInMetersSum="0.00" meanHaltingDuration="0.00" maxHaltingDuration="0.00" haltingDurationSum="0.00" meanIntervalHaltingDuration="0.00" maxIntervalHaltingDuration="0.00" intervalHaltingDurationSum="0.00" startedHalts="0.00" meanVehicleNumber="0.00" maxVehicleNumber="0" />
   <interval begin="240.00" end="360.00" id="e2_east_0" sampledSeconds="7.96" nVehEntered="6" nVehLeft="6" nVehSeen="6" meanSpeed="18.84" meanTimeLoss="0.02" meanOccupancy="1.31" maxOccupancy="25.00" meanMaxJamLengthInVehicles="0.00" meanMaxJamLengthInMeters="0.00" maxJamLengthInVehicles="0" maxJamLengthInMeters="0.00" jamLengthInVehiclesSum="0" jamLengthInMetersSum="0.00" meanHaltingDuration="0.00" maxHaltingDuration="0.00" haltingDurationSum="0.00" meanIntervalHaltingDuration="0.00" maxIntervalHaltingDuration="0.00" intervalHaltingDurationSum="0.00" startedHalts="0.00" meanVehicleNumber="0.12" maxVehicleNumber="1" />
   <interval begin="240.00" end="360.00" id="e2_east_1" sampledSeconds="3.34" nVehEntered="5" nVehLeft="5" nVehSeen="5" meanSpeed="19.58" meanTimeLoss="0.01" meanOccupancy="0.94" maxOccupancy="25.00" meanMaxJamLengthInVehicles="0.00" meanMaxJamLengthInMeters="0.00" maxJamLengthInVehicles="0" maxJamLengthInMeters="0.00" jamLengthInVehiclesSum="0" jamLengthInMetersSum="0.00" meanHaltingDuration="0.00" maxHaltingDuration="0.00" haltingDurationSum="0.00" meanIntervalHaltingDuration="0.00" maxIntervalHaltingDuration="0.00" intervalHaltingDurationSum="0.00" startedHalts="0.00" meanVehicleNumber="0.05" maxVehicleNumber="1" />
   <interval begin="240.00" end="360.00" id="e2_east_2" sampledSeconds="5.64" nVehEntered="7" nVehLeft="7" nVehSeen="7" meanSpeed="19.43" meanTimeLoss="0.02" meanOccupancy="0.58" maxOccupancy="25.00" meanMaxJamLengthInVehicles="0.00" meanMaxJamLengthInMeters="0.00" maxJamLengthInVehicles="0" maxJamLengthInMeters="0.00" jamLengthInVehiclesSum="0" jamLengthInMetersSum="0.00" meanHaltingDuration="0.00" maxHaltingDuration="0.00" haltingDurationSum="0.00" meanIntervalHaltingDuration="0.00" maxIntervalHaltingDuration="0.00" intervalHaltingDurationSum="0.00" startedHalts="0.00" meanVehicleNumber="0.09" maxVehicleNumber="1" />
   <interval begin="240.00" end="360.00" id="e2_east_3" sampledSeconds="0.00" nVehEntered="0" nVehLeft="0" nVehSeen="0" meanSpeed="-1.00" meanTimeLoss="-1.00" meanOccupancy="0.00" maxOccupancy="0.00" meanMaxJamLengthInVehicles="0.00" meanMaxJamLengthInMeters="0.00" maxJamLengthInVehicles="0" maxJamLengthInMeters="0.00" jamLengthInVehiclesSum="0" jamLengthInMetersSum="0.00" meanHaltingDuration="0.00" maxHaltingDuration="0.00" haltingDurationSum="0.00" meanIntervalHaltingDuration="0.00" maxIntervalHaltingDuration="0.00" intervalHaltingDurationSum="0.00" startedHalts="0.00" meanVehicleNumber="0.00" maxVehicleNumber="0" />
   <interval begin="240.00" end="360.00" id="e2_east_4" sampledSeconds="0.00" nVehEntered="0" nVehLeft="0" nVehSeen="0" meanSpeed="-1.00" meanTimeLoss="-1.00" meanOccupancy="0.00" maxOccupancy="0.00" meanMaxJamLengthInVehicles="0.00" meanMaxJamLengthInMeters="0.00" maxJamLengthInVehicles="0" maxJamLengthInMeters="0.00" jamLengthInVehiclesSum="0" jamLengthInMetersSum="0.00" meanHaltingDuration="0.00" maxHaltingDuration="0.00" haltingDurationSum="0.00" meanIntervalHaltingDuration="0.00" maxIntervalHaltingDuration="0.00" intervalHaltingDurationSum="0.00" startedHalts="0.00" meanVehicleNumber="0.00" maxVehicleNumber="0" />
   <interval begin="360.00" end="480.00" id="e2_east_0" sampledSeconds="5.13" nVehEntered="4" nVehLeft="4" nVehSeen="4" meanSpeed="19.48" meanTimeLoss="0.02" meanOccupancy="0.87" maxOccupancy="25.00" meanMaxJamLengthInVehicles="0.00" meanMaxJamLengthInMeters="0.00" maxJamLengthInVehicles="0" maxJamLengthInMeters="0.00" jamLengthInVehiclesSum="0" jamLengthInMetersSum="0.00" meanHaltingDuration="0.00" maxHaltingDuration="0.00" haltingDurationSum="0.00" meanIntervalHaltingDuration="0.00" maxIntervalHaltingDuration="0.00" intervalHaltingDurationSum="0.00" startedHalts="0.00" meanVehicleNumber="0.07" maxVehicleNumber="1" />
   <interval begin="360.00" end="480.00" id="e2_east_1" sampledSeconds="6.36" nVehEntered="8" nVehLeft="8" nVehSeen="8" meanSpeed="19.55" meanTimeLoss="0.02" meanOccupancy="1.52" maxOccupancy="25.00" meanMaxJamLengthInVehicles="0.00" meanMaxJamLengthInMeters="0.00" maxJamLengthInVehicles="0" maxJamLengthInMeters="0.00" jamLengthInVehiclesSum="0" jamLengthInMetersSum="0.00" meanHaltingDuration="0.00" maxHaltingDuration="0.00" haltingDurationSum="0.00" meanIntervalHaltingDuration="0.00" maxIntervalHaltingDuration="0.00" intervalHaltingDurationSum="0.00" startedHalts="0.00" meanVehicleNumber="0.09" maxVehicleNumber="1" />
   <interval begin="360.00" end="480.00" id="e2_east_2" sampledSeconds="6.64" nVehEntered="8" nVehLeft="7" nVehSeen="8" meanSpeed="18.83" meanTimeLoss="0.01" meanOccupancy="0.74" maxOccupancy="25.00" meanMaxJamLengthInVehicles="0.00" meanMaxJamLengthInMeters="0.00" maxJamLengthInVehicles="0" maxJamLengthInMeters="0.00" jamLengthInVehiclesSum="0" jamLengthInMetersSum="0.00" meanHaltingDuration="0.00" maxHaltingDuration="0.00" haltingDurationSum="0.00" meanIntervalHaltingDuration="0.00" maxIntervalHaltingDuration="0.00" intervalHaltingDurationSum="0.00" startedHalts="0.00" meanVehicleNumber="0.10" maxVehicleNumber="1" />
   <interval begin="360.00" end="480.00" id="e2_east_3" sampledSeconds="0.00" nVehEntered="0" nVehLeft="0" nVehSeen="0" meanSpeed="-1.00" meanTimeLoss="-1.00" meanOccupancy="0.00" maxOccupancy="0.00" meanMaxJamLengthInVehicles="0.00" meanMaxJamLengthInMeters="0.00" maxJamLengthInVehicles="0" maxJamLengthInMeters="0.00" jamLengthInVehiclesSum="0" jamLengthInMetersSum="0.00" meanHaltingDuration="0.00" maxHaltingDuration="0.00" haltingDurationSum="0.00" meanIntervalHaltingDuration="0.00" maxIntervalHaltingDuration="0.00" intervalHaltingDurationSum="0.00" startedHalts="0.00" meanVehicleNumber="0.00" maxVehicleNumber="0" />
   <interval begin="360.00" end="480.00" id="e2_east_4" sampledSeconds="0.00" nVehEntered="0" nVehLeft="0" nVehSeen="0" meanSpeed="-1.00" meanTimeLoss="-1.00" meanOccupancy="0.00" maxOccupancy="0.00" meanMaxJamLengthInVehicles="0.00" meanMaxJamLengthInMeters="0.00" maxJamLengthInVehicles="0" maxJamLengthInMeters="0.00" jamLengthInVehiclesSum="0" jamLengthInMetersSum="0.00" meanHaltingDuration="0.00" maxHaltingDuration="0.00" haltingDurationSum="0.00" meanIntervalHaltingDuration="0.00" maxIntervalHaltingDuration="0.00" intervalHaltingDurationSum="0.00" startedHalts="0.00" meanVehicleNumber="0.00" maxVehicleNumber="0" />
   <interval begin="480.00" end="600.00" id="e2_east_0" sampledSeconds="8.20" nVehEntered="6" nVehLeft="6" nVehSeen="6" meanSpeed="18.29" meanTimeLoss="0.03" meanOccupancy="1.38" maxOccupancy="25.00" meanMaxJamLengthInVehicles="0.00" meanMaxJamLengthInMeters="0.00" maxJamLengthInVehicles="0" maxJamLengthInMeters="0.00" jamLengthInVehiclesSum="0" jamLengthInMetersSum="0.00" meanHaltingDuration="0.00" maxHaltingDuration="0.00" haltingDurationSum="0.00" meanIntervalHaltingDuration="0.00" maxIntervalHaltingDuration="0.00" intervalHaltingDurationSum="0.00" startedHalts="0.00" meanVehicleNumber="0.12" maxVehicleNumber="1" />
   <interval begin="480.00" end="600.00" id="e2_east_1" sampledSeconds="4.30" nVehEntered="4" nVehLeft="4" nVehSeen="4" meanSpeed="18.58" meanTimeLoss="0.01" meanOccupancy="0.83" maxOccupancy="25.00" meanMaxJamLengthInVehicles="0.00" meanMaxJamLengthInMeters="0.00" maxJamLengthInVehicles="0" maxJamLengthInMeters="0.00" jamLengthInVehiclesSum="0" jamLengthInMetersSum="0.00" meanHaltingDuration="0.00" maxHaltingDuration="0.00" haltingDurationSum="0.00" meanIntervalHaltingDuration="0.00" maxIntervalHaltingDuration="0.00" intervalHaltingDurationSum="0.00" startedHalts="0.00" meanVehicleNumber="0.06" maxVehicleNumber="1" />
   <interval begin="480.00" end="600.00" id="e2_east_2" sampledSeconds="5.02" nVehEntered="4" nVehLeft="5" nVehSeen="5" meanSpeed="19.07" meanTimeLoss="0.02" meanOccupancy="0.73" maxOccupancy="25.00" meanMaxJamLengthInVehicles="0.00" meanMaxJamLengthInMeters="0.00" maxJamLengthInVehicles="0" maxJamLengthInMeters="0.00" jamLengthInVehiclesSum="0" jamLengthInMetersSum="0.00" meanHaltingDuration="0.00" maxHaltingDuration="0.00" haltingDurationSum="0.00" meanIntervalHaltingDuration="0.00" maxIntervalHaltingDuration="0.00" intervalHaltingDurationSum="0.00" startedHalts="0.00" meanVehicleNumber="0.08" maxVehicleNumber="1" />
   <interval begin="480.00" end="600.00" id="e2_east_3" sampledSeconds="0.00" nVehEntered="0" nVehLeft="0" nVehSeen="0" meanSpeed="-1.00" meanTimeLoss="-1.00" meanOccupancy="0.00" maxOccupancy="0.00" meanMaxJamLengthInVehicles="0.00" meanMaxJamLengthInMeters="0.00" maxJamLengthInVehicles="0" maxJamLengthInMeters="0.00" jamLengthInVehiclesSum="0" jamLengthInMetersSum="0.00" meanHaltingDuration="0.00" maxHaltingDuration="0.00" haltingDurationSum="0.00" meanIntervalHaltingDuration="0.00" maxIntervalHaltingDuration="0.00" intervalHaltingDurationSum="0.00" startedHalts="0.00" meanVehicleNumber="0.00" maxVehicleNumber="0" />
   <interval begin="480.00" end="600.00" id="e2_east_4" sampledSeconds="0.00" nVehEntered="0" nVehLeft="0" nVehSeen="0" meanSpeed="-1.00" meanTimeLoss="-1.00" meanOccupancy="0.00" maxOccupancy="0.00" meanMaxJamLengthInVehicles="0.00" meanMaxJamLengthInMeters="0.00" maxJamLengthInVehicles="0" maxJamLengthInMeters="0.00" jamLengthInVehiclesSum="0" jamLengthInMetersSum="0.00" meanHaltingDuration="0.00" maxHaltingDuration="0.00" haltingDurationSum="0.00" meanIntervalHaltingDuration="0.00" maxIntervalHaltingDuration="0.00" intervalHaltingDurationSum="0.00" startedHalts="0.00" meanVehicleNumber="0.00" maxVehicleNumber="0" />
   <interval begin="600.00" end="720.00" id="e2_east_0" sampledSeconds="9.39" nVehEntered="7" nVehLeft="7" nVehSeen="7" meanSpeed="18.00" meanTimeLoss="0.03" meanOccupancy="1.57" maxOccupancy="25.00" meanMaxJamLengthInVehicles="0.00" meanMaxJamLengthInMeters="0.00" maxJamLengthInVehicles="0" maxJamLengthInMeters="0.00" jamLengthInVehiclesSum="0" jamLengthInMetersSum="0.00" meanHaltingDuration="0.00" maxHaltingDuration="0.00" haltingDurationSum="0.00" meanIntervalHaltingDuration="0.00" maxIntervalHaltingDuration="0.00" intervalHaltingDurationSum="0.00" startedHalts="0.00" meanVehicleNumber="0.12" maxVehicleNumber="2" />
   <interval begin="600.00" end="720.00" id="e2_east_1" sampledSeconds="15.28" nVehEntered="13" nVehLeft="13" nVehSeen="13" meanSpeed="19.16" meanTimeLoss="0.02" meanOccupancy="2.52" maxOccupancy="25.00" meanMaxJamLengthInVehicles="0.00" meanMaxJamLengthInMeters="0.00" maxJamLengthInVehicles="0" maxJamLengthInMeters="0.00" jamLengthInVehiclesSum="0" jamLengthInMetersSum="0.00" meanHaltingDuration="0.00" maxHaltingDuration="0.00" haltingDurationSum="0.00" meanIntervalHaltingDuration="0.00" maxIntervalHaltingDuration="0.00" intervalHaltingDurationSum="0.00" startedHalts="0.00" meanVehicleNumber="0.20" maxVehicleNumber="1" />
   <interval begin="600.00" end="720.00" id="e2_east_2" sampledSeconds="5.82" nVehEntered="6" nVehLeft="6" nVehSeen="6" meanSpeed="19.48" meanTimeLoss="0.02" meanOccupancy="0.91" maxOccupancy="25.00" meanMaxJamLengthInVehicles="0.00" meanMaxJamLengthInMeters="0.00" maxJamLengthInVehicles="0" maxJamLengthInMeters="0.00" jamLengthInVehiclesSum="0" jamLengthInMetersSum="0.00" meanHaltingDuration="0.00" maxHaltingDuration="0.00" haltingDurationSum="0.00" meanIntervalHaltingDuration="0.00" maxIntervalHaltingDuration="0.00" intervalHaltingDurationSum="0.00" startedHalts="0.00" meanVehicleNumber="0.11" maxVehicleNumber="1" />
   <interval begin="600.00" end="720.00" id="e2_east_3" sampledSeconds="0.00" nVehEntered="0" nVehLeft="0" nVehSeen="0" meanSpeed="-1.00" meanTimeLoss="-1.00" meanOccupancy="0.00" maxOccupancy="0.00" meanMaxJamLengthInVehicles="0.00" meanMaxJamLengthInMeters="0.00" maxJamLengthInVehicles="0" maxJamLengthInMeters="0.00" jamLengthInVehiclesSum="0" jamLengthInMetersSum="0.00" meanHaltingDuration="0.00" maxHaltingDuration="0.00" haltingDurationSum="0.00" meanIntervalHaltingDuration="0.00" maxIntervalHaltingDuration="0.00" intervalHaltingDurationSum="0.00" startedHalts="0.00" meanVehicleNumber="0.00" maxVehicleNumber="0" />
   <interval begin="600.00" end="720.00" id="e2_east_4" sampledSeconds="0.00" nVehEntered="0" nVehLeft="0" nVehSeen="0" meanSpeed="-1.00" meanTimeLoss="-1.00" meanOccupancy="0.00" maxOccupancy="0.00" meanMaxJamLengthInVehicles="0.00" meanMaxJamLengthInMeters="0.00" maxJamLengthInVehicles="0" maxJamLengthInMeters="0.00" jamLengthInVehiclesSum="0" jamLengthInMetersSum="0.00" meanHaltingDuration="0.00" maxHaltingDuration="0.00" haltingDurationSum="0.00" meanIntervalHaltingDuration="0.00" maxIntervalHaltingDuration="0.00" intervalHaltingDurationSum="0.00" startedHalts="0.00" meanVehicleNumber="0.00" maxVehicleNumber="0" />
   <interval begin="720.00" end="840.00" id="e2_east_0" sampledSeconds="7.04" nVehEntered="5" nVehLeft="5" nVehSeen="5" meanSpeed="17.74" meanTimeLoss="0.02" meanOccupancy="1.17" maxOccupancy="25.00" meanMaxJamLengthInVehicles="0.00" meanMaxJamLengthInMeters="0.00" maxJamLengthInVehicles="0" maxJamLengthInMeters="0.00" jamLengthInVehiclesSum="0" jamLengthInMetersSum="0.00" meanHaltingDuration="0.00" maxHaltingDuration="0.00" haltingDurationSum="0.00" meanIntervalHaltingDuration="0.00" maxIntervalHaltingDuration="0.00" intervalHaltingDurationSum="0.00" startedHalts="0.00" meanVehicleNumber="0.10" maxVehicleNumber="1" />
   <interval begin="720.00" end="840.00" id="e2_east_1" sampledSeconds="15.27" nVehEntered="14" nVehLeft="14" nVehSeen="14" meanSpeed="19.14" meanTimeLoss="0.02" meanOccupancy="2.85" maxOccupancy="25.00" meanMaxJamLengthInVehicles="0.00" meanMaxJamLengthInMeters="0.00" maxJamLengthInVehicles="0" maxJamLengthInMeters="0.00" jamLengthInVehiclesSum="0" jamLengthInMetersSum="0.00" meanHaltingDuration="0.00" maxHaltingDuration="0.00" haltingDurationSum="0.00" meanIntervalHaltingDuration="0.00" maxIntervalHaltingDuration="0.00" intervalHaltingDurationSum="0.00" startedHalts="0.00" meanVehicleNumber="0.24" maxVehicleNumber="1" />
   <interval begin="720.00" end="840.00" id="e2_east_2" sampledSeconds="13.25" nVehEntered="12" nVehLeft="12" nVehSeen="12" meanSpeed="19.45" meanTimeLoss="0.02" meanOccupancy="1.90" maxOccupancy="25.00" meanMaxJamLengthInVehicles="0.00" meanMaxJamLengthInMeters="0.00" maxJamLengthInVehicles="0" maxJamLengthInMeters="0.00" jamLengthInVehiclesSum="0" jamLengthInMetersSum="0.00" meanHaltingDuration="0.00" maxHaltingDuration="0.00" haltingDurationSum="0.00" meanIntervalHaltingDuration="0.00" maxIntervalHaltingDuration="0.00" intervalHaltingDurationSum="0.00" startedHalts="0.00" meanVehicleNumber="0.18" maxVehicleNumber="1" />
   <interval begin="720.00" end="840.00" id="e2_east_3" sampledSeconds="0.00" nVehEntered="0" nVehLeft="0" nVehSeen="0" meanSpeed="-1.00" meanTimeLoss="-1.00" meanOccupancy="0.00" maxOccupancy="0.00" meanMaxJamLengthInVehicles="0.00" meanMaxJamLengthInMeters="0.00" maxJamLengthInVehicles="0" maxJamLengthInMeters="0.00" jamLengthInVehiclesSum="0" jamLengthInMetersSum="0.00" meanHaltingDuration="0.00" maxHaltingDuration="0.00" haltingDurationSum="0.00" meanIntervalHaltingDuration="0.00" maxIntervalHaltingDuration="0.00" intervalHaltingDurationSum="0.00" startedHalts="0.00" meanVehicleNumber="0.00" maxVehicleNumber="0" />
   <interval begin="720.00" end="840.00" id="e2_east_4" sampledSeconds="0.00" nVehEntered="0" nVehLeft="0" nVehSeen="0" meanSpeed="-1.00" meanTimeLoss="-1.00" meanOccupancy="0.00" maxOccupancy="0.00" meanMaxJamLengthInVehicles="0.00" meanMaxJamLengthInMeters="0.00" maxJamLengthInVehicles="0" maxJamLengthInMeters="0.00" jamLengthInVehiclesSum="0" jamLengthInMetersSum="0.00" meanHaltingDuration="0.00" maxHaltingDuration="0.00" haltingDurationSum="0.00" meanIntervalHaltingDuration="0.00" maxIntervalHaltingDuration="0.00" intervalHaltingDurationSum="0.00" startedHalts="0.00" meanVehicleNumber="0.00" maxVehicleNumber="0" />
   <interval begin="840.00" end="960.00" id="e2_east_0" sampledSeconds="1.39" nVehEntered="1" nVehLeft="1" nVehSeen="1" meanSpeed="17.50" meanTimeLoss="0.03" meanOccupancy="0.23" maxOccupancy="25.00" meanMaxJamLengthInVehicles="0.00" meanMaxJamLengthInMeters="0.00" maxJamLengthInVehicles="0" maxJamLengthInMeters="0.00" jamLengthInVehiclesSum="0" jamLengthInMetersSum="0.00" meanHaltingDuration="0.00" maxHaltingDuration="0.00" haltingDurationSum="0.00" meanIntervalHaltingDuration="0.00" maxIntervalHaltingDuration="0.00" intervalHaltingDurationSum="0.00" startedHalts="0.00" meanVehicleNumber="0.02" maxVehicleNumber="1" />
   <interval begin="840.00" end="960.00" id="e2_east_1" sampledSeconds="14.87" nVehEntered="15" nVehLeft="15" nVehSeen="15" meanSpeed="19.24" meanTimeLoss="0.02" meanOccupancy="2.96" maxOccupancy="25.00" meanMaxJamLengthInVehicles="0.00" meanMaxJamLengthInMeters="0.00" maxJamLengthInVehicles="0" maxJamLengthInMeters="0.00" jamLengthInVehiclesSum="0" jamLengthInMetersSum="0.00" meanHaltingDuration="0.00" maxHaltingDuration="0.00" haltingDurationSum="0.00" meanIntervalHaltingDuration="0.00" maxIntervalHaltingDuration="0.00" intervalHaltingDurationSum="0.00" startedHalts="0.00" meanVehicleNumber="0.23" maxVehicleNumber="1" />
   <interval begin="840.00" end="960.00" id="e2_east_2" sampledSeconds="19.11" nVehEntered="18" nVehLeft="18" nVehSeen="18" meanSpeed="19.08" meanTimeLoss="0.02" meanOccupancy="2.82" maxOccupancy="25.00" meanMaxJamLengthInVehicles="0.00" meanMaxJamLengthInMeters="0.00" maxJamLengthInVehicles="0" maxJamLengthInMeters="0.00" jamLengthInVehiclesSum="0" jamLengthInMetersSum="0.00" meanHaltingDuration="0.00" maxHaltingDuration="0.00" haltingDurationSum="0.00" meanIntervalHaltingDuration="0.00" maxIntervalHaltingDuration="0.00" intervalHaltingDurationSum="0.00" startedHalts="0.00" meanVehicleNumber="0.28" maxVehicleNumber="1" />
   <interval begin="840.00" end="960.00" id="e2_east_3" sampledSeconds="0.00" nVehEntered="0" nVehLeft="0" nVehSeen="0" meanSpeed="-1.00" meanTimeLoss="-1.00" meanOccupancy="0.00" maxOccupancy="0.00" meanMaxJamLengthInVehicles="0.00" meanMaxJamLengthInMeters="0.00" maxJamLengthInVehicles="0" maxJamLengthInMeters="0.00" jamLengthInVehiclesSum="0" jamLengthInMetersSum="0.00" meanHaltingDuration="0.00" maxHaltingDuration="0.00" haltingDurationSum="0.00" meanIntervalHaltingDuration="0.00" maxIntervalHaltingDuration="0.00" intervalHaltingDurationSum="0.00" startedHalts="0.00" meanVehicleNumber="0.00" maxVehicleNumber="0" />
   <interval begin="840.00" end="960.00" id="e2_east_4" sampledSeconds="0.00" nVehEntered="0" nVehLeft="0" nVehSeen="0" meanSpeed="-1.00" meanTimeLoss="-1.00" meanOccupancy="0.00" maxOccupancy="0.00" meanMaxJamLengthInVehicles="0.00" meanMaxJamLengthInMeters="0.00" maxJamLengthInVehicles="0" maxJamLengthInMeters="0.00" jamLengthInVehiclesSum="0" jamLengthInMetersSum="0.00" meanHaltingDuration="0.00" maxHaltingDuration="0.00" haltingDurationSum="0.00" meanIntervalHaltingDuration="0.00" maxIntervalHaltingDuration="0.00" intervalHaltingDurationSum="0.00" startedHalts="0.00" meanVehicleNumber="0.00" maxVehicleNumber="0" />
   <interval begin="960.00" end="1080.00" id="e2_east_0" sampledSeconds="3.01" nVehEntered="2" nVehLeft="2" nVehSeen="2" meanSpeed="16.61" meanTimeLoss="0.03" meanOccupancy="0.58" maxOccupancy="25.00" meanMaxJamLengthInVehicles="0.00" meanMaxJamLengthInMeters="0.00" maxJamLengthInVehicles="0" maxJamLengthInMeters="0.00" jamLengthInVehiclesSum="0" jamLengthInMetersSum="0.00" meanHaltingDuration="0.00" maxHaltingDuration="0.00" haltingDurationSum="0.00" meanIntervalHaltingDuration="0.00" maxIntervalHaltingDuration="0.00" intervalHaltingDurationSum="0.00" startedHalts="0.00" meanVehicleNumber="0.05" maxVehicleNumber="1" />
   <interval begin="960.00" end="1080.00" id="e2_east_1" sampledSeconds="16.50" nVehEntered="16" nVehLeft="15" nVehSeen="16" meanSpeed="19.02" meanTimeLoss="0.02" meanOccupancy="3.40" maxOccupancy="25.00" meanMaxJamLengthInVehicles="0.00" meanMaxJamLengthInMeters="0.00" maxJamLengthInVehicles="0" maxJamLengthInMeters="0.00" jamLengthInVehiclesSum="0" jamLengthInMetersSum="0.00" meanHaltingDuration="0.00" maxHaltingDuration="0.00" haltingDurationSum="0.00" meanIntervalHaltingDuration="0.00" maxIntervalHaltingDuration="0.00" intervalHaltingDurationSum="0.00" startedHalts="0.00" meanVehicleNumber="0.24" maxVehicleNumber="1" />
   <interval begin="960.00" end="1080.00" id="e2_east_2" sampledSeconds="15.05" nVehEntered="16" nVehLeft="16" nVehSeen="16" meanSpeed="19.29" meanTimeLoss="0.02" meanOccupancy="1.88" maxOccupancy="25.00" meanMaxJamLengthInVehicles="0.00" meanMaxJamLengthInMeters="0.00" maxJamLengthInVehicles="0" maxJamLengthInMeters="0.00" jamLengthInVehiclesSum="0" jamLengthInMetersSum="0.00" meanHaltingDuration="0.00" maxHaltingDuration="0.00" haltingDurationSum="0.00" meanIntervalHaltingDuration="0.00" maxIntervalHaltingDuration="0.00" intervalHaltingDurationSum="0.00" startedHalts="0.00" meanVehicleNumber="0.21" maxVehicleNumber="1" />
   <interval begin="960.00" end="1080.00" id="e2_east_3" sampledSeconds="0.00" nVehEntered="0" nVehLeft="0" nVehSeen="0" meanSpeed="-1.00" meanTimeLoss="-1.00" meanOccupancy="0.00" maxOccupancy="0.00" meanMaxJamLengthInVehicles="0.00" meanMaxJamLengthInMeters="0.00" maxJamLengthInVehicles="0" maxJamLengthInMeters="0.00" jamLengthInVehiclesSum="0" jamLengthInMetersSum="0.00" meanHaltingDuration="0.00" maxHaltingDuration="0.00" haltingDurationSum="0.00" meanIntervalHaltingDuration="0.00" maxIntervalHaltingDuration="0.00" intervalHaltingDurationSum="0.00" startedHalts="0.00" meanVehicleNumber="0.00" maxVehicleNumber="0" />
   <interval begin="960.00" end="1080.00" id="e2_east_4" sampledSeconds="0.00" nVehEntered="0" nVehLeft="0" nVehSeen="0" meanSpeed="-1.00" meanTimeLoss="-1.00" meanOccupancy="0.00" maxOccupancy="0.00" meanMaxJamLengthInVehicles="0.00" meanMaxJamLengthInMeters="0.00" maxJamLengthInVehicles="0" maxJamLengthInMeters="0.00" jamLengthInVehiclesSum="0" jamLengthInMetersSum="0.00" meanHaltingDuration="0.00" maxHaltingDuration="0.00" haltingDurationSum="0.00" meanIntervalHaltingDuration="0.00" maxIntervalHaltingDuration="0.00" intervalHaltingDurationSum="0.00" startedHalts="0.00" meanVehicleNumber="0.00" maxVehicleNumber="0" />
   <interval begin="1080.00" end="1200.00" id="e2_east_0" sampledSeconds="1.43" nVehEntered="3" nVehLeft="3" nVehSeen="3" meanSpeed="19.11" meanTimeLoss="0.01" meanOccupancy="0.54" maxOccupancy="25.00" meanMaxJamLengthInVehicles="0.00" meanMaxJamLengthInMeters="0.00" maxJamLengthInVehicles="0" maxJamLengthInMeters="0.00" jamLengthInVehiclesSum="0" jamLengthInMetersSum="0.00" meanHaltingDuration="0.00" maxHaltingDuration="0.00" haltingDurationSum="0.00" meanIntervalHaltingDuration="0.00" maxIntervalHaltingDuration="0.00" intervalHaltingDurationSum="0.00" startedHalts="0.00" meanVehicleNumber="0.03" maxVehicleNumber="1" />
   <interval begin="1080.00" end="1200.00" id="e2_east_1" sampledSeconds="22.37" nVehEntered="18" nVehLeft="19" nVehSeen="19" meanSpeed="18.86" meanTimeLoss="0.03" meanOccupancy="3.56" maxOccupancy="25.00" meanMaxJamLengthInVehicles="0.00" meanMaxJamLengthInMeters="0.00" maxJamLengthInVehicles="0" maxJamLengthInMeters="0.00" jamLengthInVehiclesSum="0" jamLengthInMetersSum="0.00" meanHaltingDuration="0.00" maxHaltingDuration="0.00" haltingDurationSum="0.00" meanIntervalHaltingDuration="0.00" maxIntervalHaltingDuration="0.00" intervalHaltingDurationSum="0.00" startedHalts="0.00" meanVehicleNumber="0.31" maxVehicleNumber="1" />
   <interval begin="1080.00" end="1200.00" id="e2_east_2" sampledSeconds="11.66" nVehEntered="11" nVehLeft="11" nVehSeen="11" meanSpeed="19.02" meanTimeLoss="0.02" meanOccupancy="1.79" maxOccupancy="25.00" meanMaxJamLengthInVehicles="0.00" meanMaxJamLengthInMeters="0.00" maxJamLengthInVehicles="0" maxJamLengthInMeters="0.00" jamLengthInVehiclesSum="0" jamLengthInMetersSum="0.00" meanHaltingDuration="0.00" maxHaltingDuration="0.00" haltingDurationSum="0.00" meanIntervalHaltingDuration="0.00" maxIntervalHaltingDuration="0.00" intervalHaltingDurationSum="0.00" startedHalts="0.00" meanVehicleNumber="0.17" maxVehicleNumber="1" />
   <interval begin="1080.00" end="1200.00" id="e2_east_3" sampledSeconds="0.00" nVehEntered="0" nVehLeft="0" nVehSeen="0" meanSpeed="-1.00" meanTimeLoss="-1.00" meanOccupancy="0.00" maxOccupancy="0.00" meanMaxJamLengthInVehicles="0.00" meanMaxJamLengthInMeters="0.00" maxJamLengthInVehicles="0" maxJamLengthInMeters="0.00" jamLengthInVehiclesSum="0" jamLengthInMetersSum="0.00" meanHaltingDuration="0.00" maxHaltingDuration="0.00" haltingDurationSum="0.00" meanIntervalHaltingDuration="0.00" maxIntervalHaltingDuration="0.00" intervalHaltingDurationSum="0.00" startedHalts="0.00" meanVehicleNumber="0.00" maxVehicleNumber="0" />
   <interval begin="1080.00" end="1200.00" id="e2_east_4" sampledSeconds="0.00" nVehEntered="0" nVehLeft="0" nVehSeen="0" meanSpeed="-1.00" meanTimeLoss="-1.00" meanOccupancy="0.00" maxOccupancy="0.00" meanMaxJamLengthInVehicles="0.00" meanMaxJamLengthInMeters="0.00" maxJamLengthInVehicles="0" maxJamLengthInMeters="0.00" jamLengthInVehiclesSum="0" jamLengthInMetersSum="0.00" meanHaltingDuration="0.00" maxHaltingDuration="0.00" haltingDurationSum="0.00" meanIntervalHaltingDuration="0.00" maxIntervalHaltingDuration="0.00" intervalHaltingDurationSum="0.00" startedHalts="0.00" meanVehicleNumber="0.00" maxVehicleNumber="0" />
   <interval begin="1200.00" end="1320.00" id="e2_east_0" sampledSeconds="6.37" nVehEntered="5" nVehLeft="5" nVehSeen="5" meanSpeed="17.60" meanTimeLoss="0.04" meanOccupancy="1.16" maxOccupancy="25.00" meanMaxJamLengthInVehicles="0.00" meanMaxJamLengthInMeters="0.00" maxJamLengthInVehicles="0" maxJamLengthInMeters="0.00" jamLengthInVehiclesSum="0" jamLengthInMetersSum="0.00" meanHaltingDuration="0.00" maxHaltingDuration="0.00" haltingDurationSum="0.00" meanIntervalHaltingDuration="0.00" maxIntervalHaltingDuration="0.00" intervalHaltingDurationSum="0.00" startedHalts="0.00" meanVehicleNumber="0.09" maxVehicleNumber="2" />
   <interval begin="1200.00" end="1320.00" id="e2_east_1" sampledSeconds="13.83" nVehEntered="13" nVehLeft="13" nVehSeen="13" meanSpeed="18.32" meanTimeLoss="0.03" meanOccupancy="2.22" maxOccupancy="25.00" meanMaxJamLengthInVehicles="0.00" meanMaxJamLengthInMeters="0.00" maxJamLengthInVehicles="0" maxJamLengthInMeters="0.00" jamLengthInVehiclesSum="0" jamLengthInMetersSum="0.00" meanHaltingDuration="0.00" maxHaltingDuration="0.00" haltingDurationSum="0.00" meanIntervalHaltingDuration="0.00" maxIntervalHaltingDuration="0.00" intervalHaltingDurationSum="0.00" startedHalts="0.00" meanVehicleNumber="0.18" maxVehicleNumber="1" />
   <interval begin="1200.00" end="1320.00" id="e2_east_2" sampledSeconds="16.59" nVehEntered="15" nVehLeft="15" nVehSeen="15" meanSpeed="18.66" meanTimeLoss="0.02" meanOccupancy="2.51" maxOccupancy="25.00" meanMaxJamLengthInVehicles="0.00" meanMaxJamLengthInMeters="0.00" maxJamLengthInVehicles="0" maxJamLengthInMeters="0.00" jamLengthInVehiclesSum="0" jamLengthInMetersSum="0.00" meanHaltingDuration="0.00" maxHaltingDuration="0.00" haltingDurationSum="0.00" meanIntervalHaltingDuration="0.00" maxIntervalHaltingDuration="0.00" intervalHaltingDurationSum="0.00" startedHalts="0.00" meanVehicleNumber="0.23" maxVehicleNumber="1" />
   <interval begin="1200.00" end="1320.00" id="e2_east_3" sampledSeconds="0.00" nVehEntered="0" nVehLeft="0" nVehSeen="0" meanSpeed="-1.00" meanTimeLoss="-1.00" meanOccupancy="0.00" maxOccupancy="0.00" meanMaxJamLengthInVehicles="0.00" meanMaxJamLengthInMeters="0.00" maxJamLengthInVehicles="0" maxJamLengthInMeters="0.00" jamLengthInVehiclesSum="0" jamLengthInMetersSum="0.00" meanHaltingDuration="0.00" maxHaltingDuration="0.00" haltingDurationSum="0.00" meanIntervalHaltingDuration="0.00" maxIntervalHaltingDuration="0.00" intervalHaltingDurationSum="0.00" startedHalts="0.00" meanVehicleNumber="0.00" maxVehicleNumber="0" />
   <interval begin="1200.00" end="1320.00" id="e2_east_4" sampledSeconds="0.00" nVehEntered="0" nVehLeft="0" nVehSeen="0" meanSpeed="-1.00" meanTimeLoss="-1.00" meanOccupancy="0.00" maxOccupancy="0.00" meanMaxJamLengthInVehicles="0.00" meanMaxJamLengthInMeters="0.00" maxJamLengthInVehicles="0" maxJamLengthInMeters="0.00" jamLengthInVehiclesSum="0" jamLengthInMetersSum="0.00" meanHaltingDuration="0.00" maxHaltingDuration="0.00" haltingDurationSum="0.00" meanIntervalHaltingDuration="0.00" maxIntervalHaltingDuration="0.00" intervalHaltingDurationSum="0.00" startedHalts="0.00" meanVehicleNumber="0.00" maxVehicleNumber="0" />
   <interval begin="1320.00" end="1440.00" id="e2_east_0" sampledSeconds="3.67" nVehEntered="3" nVehLeft="3" nVehSeen="3" meanSpeed="17.79" meanTimeLoss="0.03" meanOccupancy="0.63" maxOccupancy="25.00" meanMaxJamLengthInVehicles="0.00" meanMaxJamLengthInMeters="0.00" maxJamLengthInVehicles="0" maxJamLengthInMeters="0.00" jamLengthInVehiclesSum="0" jamLengthInMetersSum="0.00" meanHaltingDuration="0.00" maxHaltingDuration="0.00" haltingDurationSum="0.00" meanIntervalHaltingDuration="0.00" maxIntervalHaltingDuration="0.00" intervalHaltingDurationSum="0.00" startedHalts="0.00" meanVehicleNumber="0.05" maxVehicleNumber="1" />
   <interval begin="1320.00" end="1440.00" id="e2_east_1" sampledSeconds="17.39" nVehEntered="16" nVehLeft="15" nVehSeen="16" meanSpeed="18.70" meanTimeLoss="0.03" meanOccupancy="3.23" maxOccupancy="25.00" meanMaxJamLengthInVehicles="0.00" meanMaxJamLengthInMeters="0.00" maxJamLengthInVehicles="0" maxJamLengthInMeters="0.00" jamLengthInVehiclesSum="0" jamLengthInMetersSum="0.00" meanHaltingDuration="0.00" maxHaltingDuration="0.00" haltingDurationSum="0.00" meanIntervalHaltingDuration="0.00" maxIntervalHaltingDuration="0.00" intervalHaltingDurationSum="0.00" startedHalts="0.00" meanVehicleNumber="0.24" maxVehicleNumber="1" />
   <interval begin="1320.00" end="1440.00" id="e2_east_2" sampledSeconds="14.53" nVehEntered="14" nVehLeft="14" nVehSeen="14" meanSpeed="19.01" meanTimeLoss="0.02" meanOccupancy="2.06" maxOccupancy="25.00" meanMaxJamLengthInVehicles="0.00" meanMaxJamLengthInMeters="0.00" maxJamLengthInVehicles="0" maxJamLengthInMeters="0.00" jamLengthInVehiclesSum="0" jamLengthInMetersSum="0.00" meanHaltingDuration="0.00" maxHaltingDuration="0.00" haltingDurationSum="0.00" meanIntervalHaltingDuration="0.00" maxIntervalHaltingDuration="0.00" intervalHaltingDurationSum="0.00" startedHalts="0.00" meanVehicleNumber="0.24" maxVehicleNumber="1" />
   <interval begin="1320.00" end="1440.00" id="e2_east_3" sampledSeconds="0.00" nVehEntered="0" nVehLeft="0" nVehSeen="0" meanSpeed="-1.00" meanTimeLoss="-1.00" meanOccupancy="0.00" maxOccupancy="0.00" meanMaxJamLengthInVehicles="0.00" meanMaxJamLengthInMeters="0.00" maxJamLengthInVehicles="0" maxJamLengthInMeters="0.00" jamLengthInVehiclesSum="0" jamLengthInMetersSum="0.00" meanHaltingDuration="0.00" maxHaltingDuration="0.00" haltingDurationSum="0.00" meanIntervalHaltingDuration="0.00" maxIntervalHaltingDuration="0.00" intervalHaltingDurationSum="0.00" startedHalts="0.00" meanVehicleNumber="0.00" maxVehicleNumber="0" />
   <interval begin="1320.00" end="1440.00" id="e2_east_4" sampledSeconds="0.00" nVehEntered="0" nVehLeft="0" nVehSeen="0" meanSpeed="-1.00" meanTimeLoss="-1.00" meanOccupancy="0.00" maxOccupancy="0.00" meanMaxJamLengthInVehicles="0.00" meanMaxJamLengthInMeters="0.00" maxJamLengthInVehicles="0" maxJamLengthInMeters="0.00" jamLengthInVehiclesSum="0" jamLengthInMetersSum="0.00" meanHaltingDuration="0.00" maxHaltingDuration="0.00" haltingDurationSum="0.00" meanIntervalHaltingDuration="0.00" maxIntervalHaltingDuration="0.00" intervalHaltingDurationSum="0.00" startedHalts="0.00" meanVehicleNumber="0.00" maxVehicleNumber="0" />
   <interval begin="1440.00" end="1560.00" id="e2_east_0" sampledSeconds="2.88" nVehEntered="4" nVehLeft="4" nVehSeen="4" meanSpeed="17.11" meanTimeLoss="0.01" meanOccupancy="0.77" maxOccupancy="25.00" meanMaxJamLengthInVehicles="0.00" meanMaxJamLengthInMeters="0.00" maxJamLengthInVehicles="0" maxJamLengthInMeters="0.00" jamLengthInVehiclesSum="0" jamLengthInMetersSum="0.00" meanHaltingDuration="0.00" maxHaltingDuration="0.00" haltingDurationSum="0.00" meanIntervalHaltingDuration="0.00" maxIntervalHaltingDuration="0.00" intervalHaltingDurationSum="0.00" startedHalts="0.00" meanVehicleNumber="0.04" maxVehicleNumber="1" />
   <interval begin="1440.00" end="1560.00" id="e2_east_1" sampledSeconds="16.04" nVehEntered="15" nVehLeft="16" nVehSeen="16" meanSpeed="19.41" meanTimeLoss="0.02" meanOccupancy="2.60" maxOccupancy="25.00" meanMaxJamLengthInVehicles="0.00" meanMaxJamLengthInMeters="0.00" maxJamLengthInVehicles="0" maxJamLengthInMeters="0.00" jamLengthInVehiclesSum="0" jamLengthInMetersSum="0.00" meanHaltingDuration="0.00" maxHaltingDuration="0.00" haltingDurationSum="0.00" meanIntervalHaltingDuration="0.00" maxIntervalHaltingDuration="0.00" intervalHaltingDurationSum="0.00" startedHalts="0.00" meanVehicleNumber="0.23" maxVehicleNumber="1" />
   <interval begin="1440.00" end="1560.00" id="e2_east_2" sampledSeconds="15.62" nVehEntered="15" nVehLeft="15" nVehSeen="15" meanSpeed="19.05" meanTimeLoss="0.02" meanOccupancy="2.09" maxOccupancy="25.00" meanMaxJamLengthInVehicles="0.00" meanMaxJamLengthInMeters="0.00" maxJamLengthInVehicles="0" maxJamLengthInMeters="0.00" jamLengthInVehiclesSum="0" jamLengthInMetersSum="0.00" meanHaltingDuration="0.00" maxHaltingDuration="0.00" haltingDurationSum="0.00" meanIntervalHaltingDuration="0.00" maxIntervalHaltingDuration="0.00" intervalHaltingDurationSum="0.00" startedHalts="0.00" meanVehicleNumber="0.22" maxVehicleNumber="1" />
   <interval begin="1440.00" end="1560.00" id="e2_east_3" sampledSeconds="0.00" nVehEntered="0" nVehLeft="0" nVehSeen="0" meanSpeed="-1.00" meanTimeLoss="-1.00" meanOccupancy="0.00" maxOccupancy="0.00" meanMaxJamLengthInVehicles="0.00" meanMaxJamLengthInMeters="0.00" maxJamLengthInVehicles="0" maxJamLengthInMeters="0.00" jamLengthInVehiclesSum="0" jamLengthInMetersSum="0.00" meanHaltingDuration="0.00" maxHaltingDuration="0.00" haltingDurationSum="0.00" meanIntervalHaltingDuration="0.00" maxIntervalHaltingDuration="0.00" intervalHaltingDurationSum="0.00" startedHalts="0.00" meanVehicleNumber="0.00" maxVehicleNumber="0" />
   <interval begin="1440.00" end="1560.00" id="e2_east_4" sampledSeconds="0.00" nVehEntered="0" nVehLeft="0" nVehSeen="0" meanSpeed="-1.00" meanTimeLoss="-1.00" meanOccupancy="0.00" maxOccupancy="0.00" meanMaxJamLengthInVehicles="0.00" meanMaxJamLengthInMeters="0.00" maxJamLengthInVehicles="0" maxJamLengthInMeters="0.00" jamLengthInVehiclesSum="0" jamLengthInMetersSum="0.00" meanHaltingDuration="0.00" maxHaltingDuration="0.00" haltingDurationSum="0.00" meanIntervalHaltingDuration="0.00" maxIntervalHaltingDuration="0.00" intervalHaltingDurationSum="0.00" startedHalts="0.00" meanVehicleNumber="0.00" maxVehicleNumber="0" />
   <interval begin="1560.00" end="1680.00" id="e2_east_0" sampledSeconds="4.03" nVehEntered="3" nVehLeft="3" nVehSeen="3" meanSpeed="16.63" meanTimeLoss="0.02" meanOccupancy="0.73" maxOccupancy="25.00" meanMaxJamLengthInVehicles="0.00" meanMaxJamLengthInMeters="0.00" maxJamLengthInVehicles="0" maxJamLengthInMeters="0.00" jamLengthInVehiclesSum="0" jamLengthInMetersSum="0.00" meanHaltingDuration="0.00" maxHaltingDuration="0.00" haltingDurationSum="0.00" meanIntervalHaltingDuration="0.00" maxIntervalHaltingDuration="0.00" intervalHaltingDurationSum="0.00" startedHalts="0.00" meanVehicleNumber="0.06" maxVehicleNumber="1" />
   <interval begin="1560.00" end="1680.00" id="e2_east_1" sampledSeconds="8.42" nVehEntered="9" nVehLeft="9" nVehSeen="9" meanSpeed="19.12" meanTimeLoss="0.02" meanOccupancy="1.62" maxOccupancy="25.00" meanMaxJamLengthInVehicles="0.00" meanMaxJamLengthInMeters="0.00" maxJamLengthInVehicles="0" maxJamLengthInMeters="0.00" jamLengthInVehiclesSum="0" jamLengthInMetersSum="0.00" meanHaltingDuration="0.00" maxHaltingDuration="0.00" haltingDurationSum="0.00" meanIntervalHaltingDuration="0.00" maxIntervalHaltingDuration="0.00" intervalHaltingDurationSum="0.00" startedHalts="0.00" meanVehicleNumber="0.12" maxVehicleNumber="1" />
   <interval begin="1560.00" end="1680.00" id="e2_east_2" sampledSeconds="24.28" nVehEntered="19" nVehLeft="19" nVehSeen="19" meanSpeed="18.41" meanTimeLoss="0.03" meanOccupancy="3.89" maxOccupancy="25.00" meanMaxJamLengthInVehicles="0.00" meanMaxJamLengthInMeters="0.00" maxJamLengthInVehicles="0" maxJamLengthInMeters="0.00" jamLengthInVehiclesSum="0" jamLengthInMetersSum="0.00" meanHaltingDuration="0.00" maxHaltingDuration="0.00" haltingDurationSum="0.00" meanIntervalHaltingDuration="0.00" maxIntervalHaltingDuration="0.00" intervalHaltingDurationSum="0.00" startedHalts="0.00" meanVehicleNumber="0.35" maxVehicleNumber="2" />
   <interval begin="1560.00" end="1680.00" id="e2_east_3" sampledSeconds="0.00" nVehEntered="0" nVehLeft="0" nVehSeen="0" meanSpeed="-1.00" meanTimeLoss="-1.00" meanOccupancy="0.00" maxOccupancy="0.00" meanMaxJamLengthInVehicles="0.00" meanMaxJamLengthInMeters="0.00" maxJamLengthInVehicles="0" maxJamLengthInMeters="0.00" jamLengthInVehiclesSum="0" jamLengthInMetersSum="0.00" meanHaltingDuration="0.00" maxHaltingDuration="0.00" haltingDurationSum="0.00" meanIntervalHaltingDuration="0.00" maxIntervalHaltingDuration="0.00" intervalHaltingDurationSum="0.00" startedHalts="0.00" meanVehicleNumber="0.00" maxVehicleNumber="0" />
   <interval begin="1560.00" end="1680.00" id="e2_east_4" sampledSeconds="0.00" nVehEntered="0" nVehLeft="0" nVehSeen="0" meanSpeed="-1.00" meanTimeLoss="-1.00" meanOccupancy="0.00" maxOccupancy="0.00" meanMaxJamLengthInVehicles="0.00" meanMaxJamLengthInMeters="0.00" maxJamLengthInVehicles="0" maxJamLengthInMeters="0.00" jamLengthInVehiclesSum="0" jamLengthInMetersSum="0.00" meanHaltingDuration="0.00" maxHaltingDuration="0.00" haltingDurationSum="0.00" meanIntervalHaltingDuration="0.00" maxIntervalHaltingDuration="0.00" intervalHaltingDurationSum="0.00" startedHalts="0.00" meanVehicleNumber="0.00" maxVehicleNumber="0" />
   <interval begin="1680.00" end="1800.00" id="e2_east_0" sampledSeconds="3.07" nVehEntered="2" nVehLeft="2" nVehSeen="2" meanSpeed="16.31" meanTimeLoss="0.04" meanOccupancy="0.42" maxOccupancy="25.00" meanMaxJamLengthInVehicles="0.00" meanMaxJamLengthInMeters="0.00" maxJamLengthInVehicles="0" maxJamLengthInMeters="0.00" jamLengthInVehiclesSum="0" jamLengthInMetersSum="0.00" meanHaltingDuration="0.00" maxHaltingDuration="0.00" haltingDurationSum="0.00" meanIntervalHaltingDuration="0.00" maxIntervalHaltingDuration="0.00" intervalHaltingDurationSum="0.00" startedHalts="0.00" meanVehicleNumber="0.03" maxVehicleNumber="1" />
   <interval begin="1680.00" end="1800.00" id="e2_east_1" sampledSeconds="15.03" nVehEntered="13" nVehLeft="13" nVehSeen="13" meanSpeed="18.89" meanTimeLoss="0.02" meanOccupancy="2.74" maxOccupancy="25.00" meanMaxJamLengthInVehicles="0.00" meanMaxJamLengthInMeters="0.00" maxJamLengthInVehicles="0" maxJamLengthInMeters="0.00" jamLengthInVehiclesSum="0" jamLengthInMetersSum="0.00" meanHaltingDuration="0.00" maxHaltingDuration="0.00" haltingDurationSum="0.00" meanIntervalHaltingDuration="0.00" maxIntervalHaltingDuration="0.00" intervalHaltingDurationSum="0.00" startedHalts="0.00" meanVehicleNumber="0.20" maxVehicleNumber="1" />
   <interval begin="1680.00" end="1800.00" id="e2_east_2" sampledSeconds="16.50" nVehEntered="16" nVehLeft="16" nVehSeen="16" meanSpeed="19.16" meanTimeLoss="0.02" meanOccupancy="2.38" maxOccupancy="25.00" meanMaxJamLengthInVehicles="0.00" meanMaxJamLengthInMeters="0.00" maxJamLengthInVehicles="0" maxJamLengthInMeters="0.00" jamLengthInVehiclesSum="0" jamLengthInMetersSum="0.00" meanHaltingDuration="0.00" maxHaltingDuration="0.00" haltingDurationSum="0.00" meanIntervalHaltingDuration="0.00" maxIntervalHaltingDuration="0.00" intervalHaltingDurationSum="0.00" startedHalts="0.00" meanVehicleNumber="0.25" maxVehicleNumber="1" />
   <interval begin="1680.00" end="1800.00" id="e2_east_3" sampledSeconds="0.00" nVehEntered="0" nVehLeft="0" nVehSeen="0" meanSpeed="-1.00" meanTimeLoss="-1.00" meanOccupancy="0.00" maxOccupancy="0.00" meanMaxJamLengthInVehicles="0.00" meanMaxJamLengthInMeters="0.00" maxJamLengthInVehicles="0" maxJamLengthInMeters="0.00" jamLengthInVehiclesSum="0" jamLengthInMetersSum="0.00" meanHaltingDuration="0.00" maxHaltingDuration="0.00" haltingDurationSum="0.00" meanIntervalHaltingDuration="0.00" maxIntervalHaltingDuration="0.00" intervalHaltingDurationSum="0.00" startedHalts="0.00" meanVehicleNumber="0.00" maxVehicleNumber="0" />
   <interval begin="1680.00" end="1800.00" id="e2_east_4" sampledSeconds="0.00" nVehEntered="0" nVehLeft="0" nVehSeen="0" meanSpeed="-1.00" meanTimeLoss="-1.00" meanOccupancy="0.00" maxOccupancy="0.00" meanMaxJamLengthInVehicles="0.00" meanMaxJamLengthInMeters="0.00" maxJamLengthInVehicles="0" maxJamLengthInMeters="0.00" jamLengthInVehiclesSum="0" jamLengthInMetersSum="0.00" meanHaltingDuration="0.00" maxHaltingDuration="0.00" haltingDurationSum="0.00" meanIntervalHaltingDuration="0.00" maxIntervalHaltingDuration="0.00" intervalHaltingDurationSum="0.00" startedHalts="0.00" meanVehicleNumber="0.00" maxVehicleNumber="0" />
   <interval begin="1800.00" end="1920.00" id="e2_east_0" sampledSeconds="13.91" nVehEntered="12" nVehLeft="12" nVehSeen="12" meanSpeed="16.54" meanTimeLoss="0.14" meanOccupancy="2.74" maxOccupancy="25.00" meanMaxJamLengthInVehicles="0.00" meanMaxJamLengthInMeters="0.00" maxJamLengthInVehicles="0" maxJamLengthInMeters="0.00" jamLengthInVehiclesSum="0" jamLengthInMetersSum="0.00" meanHaltingDuration="0.00" maxHaltingDuration="0.00" haltingDurationSum="0.00" meanIntervalHaltingDuration="0.00" maxIntervalHaltingDuration="0.00" intervalHaltingDurationSum="0.00" startedHalts="0.00" meanVehicleNumber="0.20" maxVehicleNumber="1" />
   <interval begin="1800.00" end="1920.00" id="e2_east_1" sampledSeconds="38.75" nVehEntered="22" nVehLeft="21" nVehSeen="22" meanSpeed="11.17" meanTimeLoss="0.74" meanOccupancy="6.21" maxOccupancy="25.00" meanMaxJamLengthInVehicles="0.00" meanMaxJamLengthInMeters="0.00" maxJamLengthInVehicles="0" maxJamLengthInMeters="0.00" jamLengthInVehiclesSum="0" jamLengthInMetersSum="0.00" meanHaltingDuration="1.00" maxHaltingDuration="1.00" haltingDurationSum="2.00" meanIntervalHaltingDuration="1.00" maxIntervalHaltingDuration="1.00" intervalHaltingDurationSum="2.00" startedHalts="2.00" meanVehicleNumber="0.48" maxVehicleNumber="2" />
   <interval begin="1800.00" end="1920.00" id="e2_east_2" sampledSeconds="98.30" nVehEntered="33" nVehLeft="30" nVehSeen="33" meanSpeed="7.58" meanTimeLoss="1.83" meanOccupancy="17.93" maxOccupancy="72.17" meanMaxJamLengthInVehicles="0.17" meanMaxJamLengthInMeters="0.98" maxJamLengthInVehicles="3" maxJamLengthInMeters="19.54" jamLengthInVehiclesSum="21" jamLengthInMetersSum="118.00" meanHaltingDuration="4.60" maxHaltingDuration="13.00" haltingDurationSum="23.00" meanIntervalHaltingDuration="4.60" maxIntervalHaltingDuration="13.00" intervalHaltingDurationSum="23.00" startedHalts="8.00" meanVehicleNumber="1.07" maxVehicleNumber="3" />
   <interval begin="1800.00" end="1920.00" id="e2_east_3" sampledSeconds="0.00" nVehEntered="0" nVehLeft="0" nVehSeen="0" meanSpeed="-1.00" meanTimeLoss="-1.00" meanOccupancy="0.00" maxOccupancy="0.00" meanMaxJamLengthInVehicles="0.00" meanMaxJamLengthInMeters="0.00" maxJamLengthInVehicles="0" maxJamLengthInMeters="0.00" jamLengthInVehiclesSum="0" jamLengthInMetersSum="0.00" meanHaltingDuration="0.00" maxHaltingDuration="0.00" haltingDurationSum="0.00" meanIntervalHaltingDuration="0.00" maxIntervalHaltingDuration="0.00" intervalHaltingDurationSum="0.00" startedHalts="0.00" meanVehicleNumber="0.00" maxVehicleNumber="0" />
   <interval begin="1800.00" end="1920.00" id="e2_east_4" sampledSeconds="0.00" nVehEntered="0" nVehLeft="0" nVehSeen="0" meanSpeed="-1.00" meanTimeLoss="-1.00" meanOccupancy="0.00" maxOccupancy="0.00" meanMaxJamLengthInVehicles="0.00" meanMaxJamLengthInMeters="0.00" maxJamLengthInVehicles="0" maxJamLengthInMeters="0.00" jamLengthInVehiclesSum="0" jamLengthInMetersSum="0.00" meanHaltingDuration="0.00" maxHaltingDuration="0.00" haltingDurationSum="0.00" meanIntervalHaltingDuration="0.00" maxIntervalHaltingDuration="0.00" intervalHaltingDurationSum="0.00" startedHalts="0.00" meanVehicleNumber="0.00" maxVehicleNumber="0" />
   <interval begin="1920.00" end="2040.00" id="e2_east_0" sampledSeconds="178.76" nVehEntered="25" nVehLeft="24" nVehSeen="25" meanSpeed="3.27" meanTimeLoss="5.93" meanOccupancy="33.14" maxOccupancy="72.16" meanMaxJamLengthInVehicles="0.89" meanMaxJamLengthInMeters="5.64" maxJamLengthInVehicles="3" maxJamLengthInMeters="19.45" jamLengthInVehiclesSum="107" jamLengthInMetersSum="677.09" meanHaltingDuration="36.67" maxHaltingDuration="40.00" haltingDurationSum="110.00" meanIntervalHaltingDuration="36.67" maxIntervalHaltingDuration="40.00" intervalHaltingDurationSum="110.00" startedHalts="3.00" meanVehicleNumber="1.69" maxVehicleNumber="3" />
   <interval begin="1920.00" end="2040.00" id="e2_east_1" sampledSeconds="196.30" nVehEntered="18" nVehLeft="19" nVehSeen="19" meanSpeed="2.03" meanTimeLoss="9.26" meanOccupancy="35.47" maxOccupancy="72.16" meanMaxJamLengthInVehicles="1.00" meanMaxJamLengthInMeters="6.25" maxJamLengthInVehicles="3" maxJamLengthInMeters="19.44" jamLengthInVehiclesSum="120" jamLengthInMetersSum="750.54" meanHaltingDuration="18.14" maxHaltingDuration="42.00" haltingDurationSum="127.00" meanIntervalHaltingDuration="18.14" maxIntervalHaltingDuration="42.00" intervalHaltingDurationSum="127.00" startedHalts="7.00" meanVehicleNumber="1.77" maxVehicleNumber="3" />
   <interval begin="1920.00" end="2040.00" id="e2_east_2" sampledSeconds="256.18" nVehEntered="28" nVehLeft="30" nVehSeen="31" meanSpeed="2.67" meanTimeLoss="7.13" meanOccupancy="48.02" maxOccupancy="72.16" meanMaxJamLengthInVehicles="1.28" meanMaxJamLengthInMeters="8.19" maxJamLengthInVehicles="3" maxJamLengthInMeters="19.45" jamLengthInVehiclesSum="154" jamLengthInMetersSum="982.88" meanHaltingDuration="29.33" maxHaltingDuration="47.00" haltingDurationSum="176.00" meanIntervalHaltingDuration="25.83" maxIntervalHaltingDuration="47.00" intervalHaltingDurationSum="155.00" startedHalts="5.00" meanVehicleNumber="2.37" maxVehicleNumber="3" />
   <interval begin="1920.00" end="2040.00" id="e2_east_3" sampledSeconds="0.00" nVehEntered="0" nVehLeft="0" nVehSeen="0" meanSpeed="-1.00" meanTimeLoss="-1.00" meanOccupancy="0.00" maxOccupancy="0.00" meanMaxJamLengthInVehicles="0.00" meanMaxJamLengthInMeters="0.00" maxJamLengthInVehicles="0" maxJamLengthInMeters="0.00" jamLengthInVehiclesSum="0" jamLengthInMetersSum="0.00" meanHaltingDuration="0.00" maxHaltingDuration="0.00" haltingDurationSum="0.00" meanIntervalHaltingDuration="0.00" maxIntervalHaltingDuration="0.00" intervalHaltingDurationSum="0.00" startedHalts="0.00" meanVehicleNumber="0.00" maxVehicleNumber="0" />
   <interval begin="1920.00" end="2040.00" id="e2_east_4" sampledSeconds="0.00" nVehEntered="0" nVehLeft="0" nVehSeen="0" meanSpeed="-1.00" meanTimeLoss="-1.00" meanOccupancy="0.00" maxOccupancy="0.00" meanMaxJamLengthInVehicles="0.00" meanMaxJamLengthInMeters="0.00" maxJamLengthInVehicles="0" maxJamLengthInMeters="0.00" jamLengthInVehiclesSum="0" jamLengthInMetersSum="0.00" meanHaltingDuration="0.00" maxHaltingDuration="0.00" haltingDurationSum="0.00" meanIntervalHaltingDuration="0.00" maxIntervalHaltingDuration="0.00" intervalHaltingDurationSum="0.00" startedHalts="0.00" meanVehicleNumber="0.00" maxVehicleNumber="0" />
   <interval begin="2040.00" end="2160.00" id="e2_east_0" sampledSeconds="59.94" nVehEntered="25" nVehLeft="26" nVehSeen="26" meanSpeed="10.48" meanTimeLoss="1.07" meanOccupancy="9.86" maxOccupancy="50.00" meanMaxJamLengthInVehicles="0.06" meanMaxJamLengthInMeters="0.23" maxJamLengthInVehicles="1" maxJamLengthInMeters="5.00" jamLengthInVehiclesSum="7" jamLengthInMetersSum="27.99" meanHaltingDuration="3.33" maxHaltingDuration="7.00" haltingDurationSum="10.00" meanIntervalHaltingDuration="3.33" maxIntervalHaltingDuration="7.00" intervalHaltingDurationSum="10.00" startedHalts="3.00" meanVehicleNumber="0.68" maxVehicleNumber="3" />
   <interval begin="2040.00" end="2160.00" id="e2_east_1" sampledSeconds="60.32" nVehEntered="19" nVehLeft="19" nVehSeen="19" meanSpeed="6.59" meanTimeLoss="2.07" meanOccupancy="9.90" maxOccupancy="64.80" meanMaxJamLengthInVehicles="0.12" meanMaxJamLengthInMeters="0.68" maxJamLengthInVehicles="2" maxJamLengthInMeters="13.96" jamLengthInVehiclesSum="15" jamLengthInMetersSum="81.56" meanHaltingDuration="6.00" maxHaltingDuration="9.00" haltingDurationSum="18.00" meanIntervalHaltingDuration="6.00" maxIntervalHaltingDuration="9.00" intervalHaltingDurationSum="18.00" startedHalts="3.00" meanVehicleNumber="0.64" maxVehicleNumber="3" />
   <interval begin="2040.00" end="2160.00" id="e2_east_2" sampledSeconds="142.78" nVehEntered="44" nVehLeft="45" nVehSeen="45" meanSpeed="7.53" meanTimeLoss="1.94" meanOccupancy="25.93" maxOccupancy="72.16" meanMaxJamLengthInVehicles="0.33" meanMaxJamLengthInMeters="2.00" maxJamLengthInVehicles="3" maxJamLengthInMeters="19.52" jamLengthInVehiclesSum="39" jamLengthInMetersSum="239.60" meanHaltingDuration="10.50" maxHaltingDuration="17.00" haltingDurationSum="42.00" meanIntervalHaltingDuration="10.50" maxIntervalHaltingDuration="17.00" intervalHaltingDurationSum="42.00" startedHalts="5.00" meanVehicleNumber="1.57" maxVehicleNumber="3" />
   <interval begin="2040.00" end="2160.00" id="e2_east_3" sampledSeconds="0.00" nVehEntered="0" nVehLeft="0" nVehSeen="0" meanSpeed="-1.00" meanTimeLoss="-1.00" meanOccupancy="0.00" maxOccupancy="0.00" meanMaxJamLengthInVehicles="0.00" meanMaxJamLengthInMeters="0.00" maxJamLengthInVehicles="0" maxJamLengthInMeters="0.00" jamLengthInVehiclesSum="0" jamLengthInMetersSum="0.00" meanHaltingDuration="0.00" maxHaltingDuration="0.00" haltingDurationSum="0.00" meanIntervalHaltingDuration="0.00" maxIntervalHaltingDuration="0.00" intervalHaltingDurationSum="0.00" startedHalts="0.00" meanVehicleNumber="0.00" maxVehicleNumber="0" />
   <interval begin="2040.00" end="2160.00" id="e2_east_4" sampledSeconds="0.00" nVehEntered="0" nVehLeft="0" nVehSeen="0" meanSpeed="-1.00" meanTimeLoss="-1.00" meanOccupancy="0.00" maxOccupancy="0.00" meanMaxJamLengthInVehicles="0.00" meanMaxJamLengthInMeters="0.00" maxJamLengthInVehicles="0" maxJamLengthInMeters="0.00" jamLengthInVehiclesSum="0" jamLengthInMetersSum="0.00" meanHaltingDuration="0.00" maxHaltingDuration="0.00" haltingDurationSum="0.00" meanIntervalHaltingDuration="0.00" maxIntervalHaltingDuration="0.00" intervalHaltingDurationSum="0.00" startedHalts="0.00" meanVehicleNumber="0.00" maxVehicleNumber="0" />
   <interval begin="2160.00" end="2280.00" id="e2_east_0" sampledSeconds="30.07" nVehEntered="21" nVehLeft="21" nVehSeen="21" meanSpeed="17.33" meanTimeLoss="0.08" meanOccupancy="5.04" maxOccupancy="25.00" meanMaxJamLengthInVehicles="0.00" meanMaxJamLengthInMeters="0.00" maxJamLengthInVehicles="0" maxJamLengthInMeters="0.00" jamLengthInVehiclesSum="0" jamLengthInMetersSum="0.00" meanHaltingDuration="0.00" maxHaltingDuration="0.00" haltingDurationSum="0.00" meanIntervalHaltingDuration="0.00" maxIntervalHaltingDuration="0.00" intervalHaltingDurationSum="0.00" startedHalts="0.00" meanVehicleNumber="0.42" maxVehicleNumber="1" />
   <interval begin="2160.00" end="2280.00" id="e2_east_1" sampledSeconds="23.93" nVehEntered="15" nVehLeft="15" nVehSeen="15" meanSpeed="14.09" meanTimeLoss="0.41" meanOccupancy="3.74" maxOccupancy="25.00" meanMaxJamLengthInVehicles="0.00" meanMaxJamLengthInMeters="0.00" maxJamLengthInVehicles="0" maxJamLengthInMeters="0.00" jamLengthInVehiclesSum="0" jamLengthInMetersSum="0.00" meanHaltingDuration="0.00" maxHaltingDuration="0.00" haltingDurationSum="0.00" meanIntervalHaltingDuration="0.00" maxIntervalHaltingDuration="0.00" intervalHaltingDurationSum="0.00" startedHalts="0.00" meanVehicleNumber="0.31" maxVehicleNumber="1" />
   <interval begin="2160.00" end="2280.00" id="e2_east_2" sampledSeconds="83.51" nVehEntered="42" nVehLeft="41" nVehSeen="42" meanSpeed="12.09" meanTimeLoss="0.75" meanOccupancy="14.28" maxOccupancy="50.00" meanMaxJamLengthInVehicles="0.01" meanMaxJamLengthInMeters="0.03" maxJamLengthInVehicles="1" maxJamLengthInMeters="3.27" jamLengthInVehiclesSum="1" jamLengthInMetersSum="3.27" meanHaltingDuration="2.00" maxHaltingDuration="2.00" haltingDurationSum="2.00" meanIntervalHaltingDuration="2.00" maxIntervalHaltingDuration="2.00" intervalHaltingDurationSum="2.00" startedHalts="1.00" meanVehicleNumber="1.02" maxVehicleNumber="3" />
   <interval begin="2160.00" end="2280.00" id="e2_east_3" sampledSeconds="0.00" nVehEntered="0" nVehLeft="0" nVehSeen="0" meanSpeed="-1.00" meanTimeLoss="-1.00" meanOccupancy="0.00" maxOccupancy="0.00" meanMaxJamLengthInVehicles="0.00" meanMaxJamLengthInMeters="0.00" maxJamLengthInVehicles="0" maxJamLengthInMeters="0.00" jamLengthInVehiclesSum="0" jamLengthInMetersSum="0.00" meanHaltingDuration="0.00" maxHaltingDuration="0.00" haltingDurationSum="0.00" meanIntervalHaltingDuration="0.00" maxIntervalHaltingDuration="0.00" intervalHaltingDurationSum="0.00" startedHalts="0.00" meanVehicleNumber="0.00" maxVehicleNumber="0" />
   <interval begin="2160.00" end="2280.00" id="e2_east_4" sampledSeconds="0.00" nVehEntered="0" nVehLeft="0" nVehSeen="0" meanSpeed="-1.00" meanTimeLoss="-1.00" meanOccupancy="0.00" maxOccupancy="0.00" meanMaxJamLengthInVehicles="0.00" meanMaxJamLengthInMeters="0.00" maxJamLengthInVehicles="0" maxJamLengthInMeters="0.00" jamLengthInVehiclesSum="0" jamLengthInMetersSum="0.00" meanHaltingDuration="0.00" maxHaltingDuration="0.00" haltingDurationSum="0.00" meanIntervalHaltingDuration="0.00" maxIntervalHaltingDuration="0.00" intervalHaltingDurationSum="0.00" startedHalts="0.00" meanVehicleNumber="0.00" maxVehicleNumber="0" />
   <interval begin="2280.00" end="2400.00" id="e2_east_0" sampledSeconds="22.45" nVehEntered="18" nVehLeft="17" nVehSeen="18" meanSpeed="17.35" meanTimeLoss="0.11" meanOccupancy="4.32" maxOccupancy="25.00" meanMaxJamLengthInVehicles="0.00" meanMaxJamLengthInMeters="0.00" maxJamLengthInVehicles="0" maxJamLengthInMeters="0.00" jamLengthInVehiclesSum="0" jamLengthInMetersSum="0.00" meanHaltingDuration="0.00" maxHaltingDuration="0.00" haltingDurationSum="0.00" meanIntervalHaltingDuration="0.00" maxIntervalHaltingDuration="0.00" intervalHaltingDurationSum="0.00" startedHalts="0.00" meanVehicleNumber="0.33" maxVehicleNumber="1" />
   <interval begin="2280.00" end="2400.00" id="e2_east_1" sampledSeconds="28.43" nVehEntered="19" nVehLeft="19" nVehSeen="19" meanSpeed="13.71" meanTimeLoss="0.42" meanOccupancy="4.02" maxOccupancy="25.00" meanMaxJamLengthInVehicles="0.00" meanMaxJamLengthInMeters="0.00" maxJamLengthInVehicles="0" maxJamLengthInMeters="0.00" jamLengthInVehiclesSum="0" jamLengthInMetersSum="0.00" meanHaltingDuration="0.00" maxHaltingDuration="0.00" haltingDurationSum="0.00" meanIntervalHaltingDuration="0.00" maxIntervalHaltingDuration="0.00" intervalHaltingDurationSum="0.00" startedHalts="0.00" meanVehicleNumber="0.36" maxVehicleNumber="1" />
   <interval begin="2280.00" end="2400.00" id="e2_east_2" sampledSeconds="88.85" nVehEntered="42" nVehLeft="43" nVehSeen="43" meanSpeed="11.69" meanTimeLoss="0.84" meanOccupancy="15.32" maxOccupancy="50.00" meanMaxJamLengthInVehicles="0.02" meanMaxJamLengthInMeters="0.08" maxJamLengthInVehicles="1" maxJamLengthInMeters="5.00" jamLengthInVehiclesSum="2" jamLengthInMetersSum="9.17" meanHaltingDuration="2.00" maxHaltingDuration="2.00" haltingDurationSum="4.00" meanIntervalHaltingDuration="2.00" maxIntervalHaltingDuration="2.00" intervalHaltingDurationSum="4.00" startedHalts="2.00" meanVehicleNumber="1.09" maxVehicleNumber="3" />
   <interval begin="2280.00" end="2400.00" id="e2_east_3" sampledSeconds="0.00" nVehEntered="0" nVehLeft="0" nVehSeen="0" meanSpeed="-1.00" meanTimeLoss="-1.00" meanOccupancy="0.00" maxOccupancy="0.00" meanMaxJamLengthInVehicles="0.00" meanMaxJamLengthInMeters="0.00" maxJamLengthInVehicles="0" maxJamLengthInMeters="0.00" jamLengthInVehiclesSum="0" jamLengthInMetersSum="0.00" meanHaltingDuration="0.00" maxHaltingDuration="0.00" haltingDurationSum="0.00" meanIntervalHaltingDuration="0.00" maxIntervalHaltingDuration="0.00" intervalHaltingDurationSum="0.00" startedHalts="0.00" meanVehicleNumber="0.00" maxVehicleNumber="0" />
   <interval begin="2280.00" end="2400.00" id="e2_east_4" sampledSeconds="0.00" nVehEntered="0" nVehLeft="0" nVehSeen="0" meanSpeed="-1.00" meanTimeLoss="-1.00" meanOccupancy="0.00" maxOccupancy="0.00" meanMaxJamLengthInVehicles="0.00" meanMaxJamLengthInMeters="0.00" maxJamLengthInVehicles="0" maxJamLengthInMeters="0.00" jamLengthInVehiclesSum="0" jamLengthInMetersSum="0.00" meanHaltingDuration="0.00" maxHaltingDuration="0.00" haltingDurationSum="0.00" meanIntervalHaltingDuration="0.00" maxIntervalHaltingDuration="0.00" intervalHaltingDurationSum="0.00" startedHalts="0.00" meanVehicleNumber="0.00" maxVehicleNumber="0" />
   <interval begin="2400.00" end="2520.00" id="e2_east_0" sampledSeconds="31.55" nVehEntered="22" nVehLeft="23" nVehSeen="23" meanSpeed="16.44" meanTimeLoss="0.15" meanOccupancy="5.37" maxOccupancy="25.00" meanMaxJamLengthInVehicles="0.00" meanMaxJamLengthInMeters="0.00" maxJamLengthInVehicles="0" maxJamLengthInMeters="0.00" jamLengthInVehiclesSum="0" jamLengthInMetersSum="0.00" meanHaltingDuration="0.00" maxHaltingDuration="0.00" haltingDurationSum="0.00" meanIntervalHaltingDuration="0.00" maxIntervalHaltingDuration="0.00" intervalHaltingDurationSum="0.00" startedHalts="0.00" meanVehicleNumber="0.44" maxVehicleNumber="2" />
   <interval begin="2400.00" end="2520.00" id="e2_east_1" sampledSeconds="32.61" nVehEntered="18" nVehLeft="18" nVehSeen="18" meanSpeed="10.97" meanTimeLoss="0.77" meanOccupancy="4.81" maxOccupancy="25.00" meanMaxJamLengthInVehicles="0.02" meanMaxJamLengthInMeters="0.06" maxJamLengthInVehicles="1" maxJamLengthInMeters="4.03" jamLengthInVehiclesSum="2" jamLengthInMetersSum="7.27" meanHaltingDuration="3.00" maxHaltingDuration="3.00" haltingDurationSum="3.00" meanIntervalHaltingDuration="3.00" maxIntervalHaltingDuration="3.00" intervalHaltingDurationSum="3.00" startedHalts="1.00" meanVehicleNumber="0.38" maxVehicleNumber="1" />
   <interval begin="2400.00" end="2520.00" id="e2_east_2" sampledSeconds="94.62" nVehEntered="41" nVehLeft="40" nVehSeen="41" meanSpeed="10.11" meanTimeLoss="1.10" meanOccupancy="16.49" maxOccupancy="62.65" meanMaxJamLengthInVehicles="0.03" meanMaxJamLengthInMeters="0.14" maxJamLengthInVehicles="1" maxJamLengthInMeters="4.45" jamLengthInVehiclesSum="4" jamLengthInMetersSum="16.71" meanHaltingDuration="3.00" maxHaltingDuration="5.00" haltingDurationSum="6.00" meanIntervalHaltingDuration="3.00" maxIntervalHaltingDuration="5.00" intervalHaltingDurationSum="6.00" startedHalts="3.00" meanVehicleNumber="1.12" maxVehicleNumber="3" />
   <interval begin="2400.00" end="2520.00" id="e2_east_3" sampledSeconds="0.00" nVehEntered="0" nVehLeft="0" nVehSeen="0" meanSpeed="-1.00" meanTimeLoss="-1.00" meanOccupancy="0.00" maxOccupancy="0.00" meanMaxJamLengthInVehicles="0.00" meanMaxJamLengthInMeters="0.00" maxJamLengthInVehicles="0" maxJamLengthInMeters="0.00" jamLengthInVehiclesSum="0" jamLengthInMetersSum="0.00" meanHaltingDuration="0.00" maxHaltingDuration="0.00" haltingDurationSum="0.00" meanIntervalHaltingDuration="0.00" maxIntervalHaltingDuration="0.00" intervalHaltingDurationSum="0.00" startedHalts="0.00" meanVehicleNumber="0.00" maxVehicleNumber="0" />
   <interval begin="2400.00" end="2520.00" id="e2_east_4" sampledSeconds="0.00" nVehEntered="0" nVehLeft="0" nVehSeen="0" meanSpeed="-1.00" meanTimeLoss="-1.00" meanOccupancy="0.00" maxOccupancy="0.00" meanMaxJamLengthInVehicles="0.00" meanMaxJamLengthInMeters="0.00" maxJamLengthInVehicles="0" maxJamLengthInMeters="0.00" jamLengthInVehiclesSum="0" jamLengthInMetersSum="0.00" meanHaltingDuration="0.00" maxHaltingDuration="0.00" haltingDurationSum="0.00" meanIntervalHaltingDuration="0.00" maxIntervalHaltingDuration="0.00" intervalHaltingDurationSum="0.00" startedHalts="0.00" meanVehicleNumber="0.00" maxVehicleNumber="0" />
   <interval begin="2520.00" end="2640.00" id="e2_east_0" sampledSeconds="30.70" nVehEntered="22" nVehLeft="22" nVehSeen="22" meanSpeed="16.91" meanTimeLoss="0.11" meanOccupancy="5.62" maxOccupancy="25.00" meanMaxJamLengthInVehicles="0.00" meanMaxJamLengthInMeters="0.00" maxJamLengthInVehicles="0" maxJamLengthInMeters="0.00" jamLengthInVehiclesSum="0" jamLengthInMetersSum="0.00" meanHaltingDuration="0.00" maxHaltingDuration="0.00" haltingDurationSum="0.00" meanIntervalHaltingDuration="0.00" maxIntervalHaltingDuration="0.00" intervalHaltingDurationSum="0.00" startedHalts="0.00" meanVehicleNumber="0.45" maxVehicleNumber="2" />
   <interval begin="2520.00" end="2640.00" id="e2_east_1" sampledSeconds="25.07" nVehEntered="16" nVehLeft="16" nVehSeen="16" meanSpeed="13.70" meanTimeLoss="0.45" meanOccupancy="3.81" maxOccupancy="25.00" meanMaxJamLengthInVehicles="0.00" meanMaxJamLengthInMeters="0.00" maxJamLengthInVehicles="0" maxJamLengthInMeters="0.00" jamLengthInVehiclesSum="0" jamLengthInMetersSum="0.00" meanHaltingDuration="0.00" maxHaltingDuration="0.00" haltingDurationSum="0.00" meanIntervalHaltingDuration="0.00" maxIntervalHaltingDuration="0.00" intervalHaltingDurationSum="0.00" startedHalts="0.00" meanVehicleNumber="0.32" maxVehicleNumber="2" />
   <interval begin="2520.00" end="2640.00" id="e2_east_2" sampledSeconds="77.29" nVehEntered="40" nVehLeft="41" nVehSeen="41" meanSpeed="12.86" meanTimeLoss="0.66" meanOccupancy="13.08" maxOccupancy="50.00" meanMaxJamLengthInVehicles="0.02" meanMaxJamLengthInMeters="0.05" maxJamLengthInVehicles="1" maxJamLengthInMeters="3.69" jamLengthInVehiclesSum="2" jamLengthInMetersSum="6.01" meanHaltingDuration="3.00" maxHaltingDuration="3.00" haltingDurationSum="3.00" meanIntervalHaltingDuration="3.00" maxIntervalHaltingDuration="3.00" intervalHaltingDurationSum="3.00" startedHalts="1.00" meanVehicleNumber="0.96" maxVehicleNumber="2" />
   <interval begin="2520.00" end="2640.00" id="e2_east_3" sampledSeconds="0.00" nVehEntered="0" nVehLeft="0" nVehSeen="0" meanSpeed="-1.00" meanTimeLoss="-1.00" meanOccupancy="0.00" maxOccupancy="0.00" meanMaxJamLengthInVehicles="0.00" meanMaxJamLengthInMeters="0.00" maxJamLengthInVehicles="0" maxJamLengthInMeters="0.00" jamLengthInVehiclesSum="0" jamLengthInMetersSum="0.00" meanHaltingDuration="0.00" maxHaltingDuration="0.00" haltingDurationSum="0.00" meanIntervalHaltingDuration="0.00" maxIntervalHaltingDuration="0.00" intervalHaltingDurationSum="0.00" startedHalts="0.00" meanVehicleNumber="0.00" maxVehicleNumber="0" />
   <interval begin="2520.00" end="2640.00" id="e2_east_4" sampledSeconds="0.00" nVehEntered="0" nVehLeft="0" nVehSeen="0" meanSpeed="-1.00" meanTimeLoss="-1.00" meanOccupancy="0.00" maxOccupancy="0.00" meanMaxJamLengthInVehicles="0.00" meanMaxJamLengthInMeters="0.00" maxJamLengthInVehicles="0" maxJamLengthInMeters="0.00" jamLengthInVehiclesSum="0" jamLengthInMetersSum="0.00" meanHaltingDuration="0.00" maxHaltingDuration="0.00" haltingDurationSum="0.00" meanIntervalHaltingDuration="0.00" maxIntervalHaltingDuration="0.00" intervalHaltingDurationSum="0.00" startedHalts="0.00" meanVehicleNumber="0.00" maxVehicleNumber="0" />
   <interval begin="2640.00" end="2760.00" id="e2_east_0" sampledSeconds="30.36" nVehEntered="18" nVehLeft="18" nVehSeen="18" meanSpeed="14.75" meanTimeLoss="0.34" meanOccupancy="5.50" maxOccupancy="25.00" meanMaxJamLengthInVehicles="0.00" meanMaxJamLengthInMeters="0.00" maxJamLengthInVehicles="0" maxJamLengthInMeters="0.00" jamLengthInVehiclesSum="0" jamLengthInMetersSum="0.00" meanHaltingDuration="0.00" maxHaltingDuration="0.00" haltingDurationSum="0.00" meanIntervalHaltingDuration="0.00" maxIntervalHaltingDuration="0.00" intervalHaltingDurationSum="0.00" startedHalts="0.00" meanVehicleNumber="0.40" maxVehicleNumber="2" />
   <interval begin="2640.00" end="2760.00" id="e2_east_1" sampledSeconds="35.99" nVehEntered="19" nVehLeft="19" nVehSeen="19" meanSpeed="11.51" meanTimeLoss="0.74" meanOccupancy="5.26" maxOccupancy="25.00" meanMaxJamLengthInVehicles="0.01" meanMaxJamLengthInMeters="0.03" maxJamLengthInVehicles="1" maxJamLengthInMeters="3.68" jamLengthInVehiclesSum="1" jamLengthInMetersSum="3.68" meanHaltingDuration="1.50" maxHaltingDuration="2.00" haltingDurationSum="3.00" meanIntervalHaltingDuration="1.50" maxIntervalHaltingDuration="2.00" intervalHaltingDurationSum="3.00" startedHalts="2.00" meanVehicleNumber="0.42" maxVehicleNumber="2" />
   <interval begin="2640.00" end="2760.00" id="e2_east_2" sampledSeconds="96.35" nVehEntered="39" nVehLeft="37" nVehSeen="39" meanSpeed="9.48" meanTimeLoss="1.25" meanOccupancy="16.72" maxOccupancy="69.66" meanMaxJamLengthInVehicles="0.10" meanMaxJamLengthInMeters="0.51" maxJamLengthInVehicles="2" maxJamLengthInMeters="12.08" jamLengthInVehiclesSum="12" jamLengthInMetersSum="61.14" meanHaltingDuration="3.00" maxHaltingDuration="7.00" haltingDurationSum="9.00" meanIntervalHaltingDuration="3.00" maxIntervalHaltingDuration="7.00" intervalHaltingDurationSum="9.00" startedHalts="5.00" meanVehicleNumber="1.10" maxVehicleNumber="3" />
   <interval begin="2640.00" end="2760.00" id="e2_east_3" sampledSeconds="0.00" nVehEntered="0" nVehLeft="0" nVehSeen="0" meanSpeed="-1.00" meanTimeLoss="-1.00" meanOccupancy="0.00" maxOccupancy="0.00" meanMaxJamLengthInVehicles="0.00" meanMaxJamLengthInMeters="0.00" maxJamLengthInVehicles="0" maxJamLengthInMeters="0.00" jamLengthInVehiclesSum="0" jamLengthInMetersSum="0.00" meanHaltingDuration="0.00" maxHaltingDuration="0.00" haltingDurationSum="0.00" meanIntervalHaltingDuration="0.00" maxIntervalHaltingDuration="0.00" intervalHaltingDurationSum="0.00" startedHalts="0.00" meanVehicleNumber="0.00" maxVehicleNumber="0" />
   <interval begin="2640.00" end="2760.00" id="e2_east_4" sampledSeconds="0.00" nVehEntered="0" nVehLeft="0" nVehSeen="0" meanSpeed="-1.00" meanTimeLoss="-1.00" meanOccupancy="0.00" maxOccupancy="0.00" meanMaxJamLengthInVehicles="0.00" meanMaxJamLengthInMeters="0.00" maxJamLengthInVehicles="0" maxJamLengthInMeters="0.00" jamLengthInVehiclesSum="0" jamLengthInMetersSum="0.00" meanHaltingDuration="0.00" maxHaltingDuration="0.00" haltingDurationSum="0.00" meanIntervalHaltingDuration="0.00" maxIntervalHaltingDuration="0.00" intervalHaltingDurationSum="0.00" startedHalts="0.00" meanVehicleNumber="0.00" maxVehicleNumber="0" />
   <interval begin="2760.00" end="2880.00" id="e2_east_0" sampledSeconds="22.52" nVehEntered="17" nVehLeft="17" nVehSeen="17" meanSpeed="17.21" meanTimeLoss="0.09" meanOccupancy="3.69" maxOccupancy="25.00" meanMaxJamLengthInVehicles="0.00" meanMaxJamLengthInMeters="0.00" maxJamLengthInVehicles="0" maxJamLengthInMeters="0.00" jamLengthInVehiclesSum="0" jamLengthInMetersSum="0.00" meanHaltingDuration="0.00" maxHaltingDuration="0.00" haltingDurationSum="0.00" meanIntervalHaltingDuration="0.00" maxIntervalHaltingDuration="0.00" intervalHaltingDurationSum="0.00" startedHalts="0.00" meanVehicleNumber="0.31" maxVehicleNumber="2" />
   <interval begin="2760.00" end="2880.00" id="e2_east_1" sampledSeconds="33.40" nVehEntered="21" nVehLeft="20" nVehSeen="21" meanSpeed="11.53" meanTimeLoss="0.64" meanOccupancy="4.87" maxOccupancy="25.00" meanMaxJamLengthInVehicles="0.00" meanMaxJamLengthInMeters="0.00" maxJamLengthInVehicles="0" maxJamLengthInMeters="0.00" jamLengthInVehiclesSum="0" jamLengthInMetersSum="0.00" meanHaltingDuration="1.00" maxHaltingDuration="1.00" haltingDurationSum="1.00" meanIntervalHaltingDuration="1.00" maxIntervalHaltingDuration="1.00" intervalHaltingDurationSum="1.00" startedHalts="1.00" meanVehicleNumber="0.42" maxVehicleNumber="2" />
   <interval begin="2760.00" end="2880.00" id="e2_east_2" sampledSeconds="107.91" nVehEntered="45" nVehLeft="45" nVehSeen="47" meanSpeed="9.89" meanTimeLoss="1.14" meanOccupancy="18.48" maxOccupancy="66.18" meanMaxJamLengthInVehicles="0.04" meanMaxJamLengthInMeters="0.17" maxJamLengthInVehicles="1" maxJamLengthInMeters="4.47" jamLengthInVehiclesSum="5" jamLengthInMetersSum="19.84" meanHaltingDuration="1.75" maxHaltingDuration="4.00" haltingDurationSum="7.00" meanIntervalHaltingDuration="1.75" maxIntervalHaltingDuration="4.00" intervalHaltingDurationSum="7.00" startedHalts="6.00" meanVehicleNumber="1.23" maxVehicleNumber="3" />
   <interval begin="2760.00" end="2880.00" id="e2_east_3" sampledSeconds="0.00" nVehEntered="0" nVehLeft="0" nVehSeen="0" meanSpeed="-1.00" meanTimeLoss="-1.00" meanOccupancy="0.00" maxOccupancy="0.00" meanMaxJamLengthInVehicles="0.00" meanMaxJamLengthInMeters="0.00" maxJamLengthInVehicles="0" maxJamLengthInMeters="0.00" jamLengthInVehiclesSum="0" jamLengthInMetersSum="0.00" meanHaltingDuration="0.00" maxHaltingDuration="0.00" haltingDurationSum="0.00" meanIntervalHaltingDuration="0.00" maxIntervalHaltingDuration="0.00" intervalHaltingDurationSum="0.00" startedHalts="0.00" meanVehicleNumber="0.00" maxVehicleNumber="0" />
   <interval begin="2760.00" end="2880.00" id="e2_east_4" sampledSeconds="0.00" nVehEntered="0" nVehLeft="0" nVehSeen="0" meanSpeed="-1.00" meanTimeLoss="-1.00" meanOccupancy="0.00" maxOccupancy="0.00" meanMaxJamLengthInVehicles="0.00" meanMaxJamLengthInMeters="0.00" maxJamLengthInVehicles="0" maxJamLengthInMeters="0.00" jamLengthInVehiclesSum="0" jamLengthInMetersSum="0.00" meanHaltingDuration="0.00" maxHaltingDuration="0.00" haltingDurationSum="0.00" meanIntervalHaltingDuration="0.00" maxIntervalHaltingDuration="0.00" intervalHaltingDurationSum="0.00" startedHalts="0.00" meanVehicleNumber="0.00" maxVehicleNumber="0" />
   <interval begin="2880.00" end="3000.00" id="e2_east_0" sampledSeconds="25.91" nVehEntered="19" nVehLeft="18" nVehSeen="19" meanSpeed="16.94" meanTimeLoss="0.13" meanOccupancy="4.84" maxOccupancy="25.00" meanMaxJamLengthInVehicles="0.00" meanMaxJamLengthInMeters="0.00" maxJamLengthInVehicles="0" maxJamLengthInMeters="0.00" jamLengthInVehiclesSum="0" jamLengthInMetersSum="0.00" meanHaltingDuration="0.00" maxHaltingDuration="0.00" haltingDurationSum="0.00" meanIntervalHaltingDuration="0.00" maxIntervalHaltingDuration="0.00" intervalHaltingDurationSum="0.00" startedHalts="0.00" meanVehicleNumber="0.37" maxVehicleNumber="2" />
   <interval begin="2880.00" end="3000.00" id="e2_east_1" sampledSeconds="29.47" nVehEntered="19" nVehLeft="19" nVehSeen="20" meanSpeed="13.02" meanTimeLoss="0.47" meanOccupancy="4.51" maxOccupancy="25.00" meanMaxJamLengthInVehicles="0.00" meanMaxJamLengthInMeters="0.00" maxJamLengthInVehicles="0" maxJamLengthInMeters="0.00" jamLengthInVehiclesSum="0" jamLengthInMetersSum="0.00" meanHaltingDuration="0.00" maxHaltingDuration="0.00" haltingDurationSum="0.00" meanIntervalHaltingDuration="0.00" maxIntervalHaltingDuration="0.00" intervalHaltingDurationSum="0.00" startedHalts="0.00" meanVehicleNumber="0.38" maxVehicleNumber="2" />
   <interval begin="2880.00" end="3000.00" id="e2_east_2" sampledSeconds="90.01" nVehEntered="43" nVehLeft="42" nVehSeen="45" meanSpeed="11.36" meanTimeLoss="0.82" meanOccupancy="15.61" maxOccupancy="49.46" meanMaxJamLengthInVehicles="0.02" meanMaxJamLengthInMeters="0.06" maxJamLengthInVehicles="1" maxJamLengthInMeters="4.44" jamLengthInVehiclesSum="2" jamLengthInMetersSum="7.80" meanHaltingDuration="2.00" maxHaltingDuration="3.00" haltingDurationSum="4.00" meanIntervalHaltingDuration="2.00" maxIntervalHaltingDuration="3.00" intervalHaltingDurationSum="4.00" startedHalts="2.00" meanVehicleNumber="1.09" maxVehicleNumber="3" />
   <interval begin="2880.00" end="3000.00" id="e2_east_3" sampledSeconds="0.00" nVehEntered="0" nVehLeft="0" nVehSeen="0" meanSpeed="-1.00" meanTimeLoss="-1.00" meanOccupancy="0.00" maxOccupancy="0.00" meanMaxJamLengthInVehicles="0.00" meanMaxJamLengthInMeters="0.00" maxJamLengthInVehicles="0" maxJamLengthInMeters="0.00" jamLengthInVehiclesSum="0" jamLengthInMetersSum="0.00" meanHaltingDuration="0.00" maxHaltingDuration="0.00" haltingDurationSum="0.00" meanIntervalHaltingDuration="0.00" maxIntervalHaltingDuration="0.00" intervalHaltingDurationSum="0.00" startedHalts="0.00" meanVehicleNumber="0.00" maxVehicleNumber="0" />
   <interval begin="2880.00" end="3000.00" id="e2_east_4" sampledSeconds="0.00" nVehEntered="0" nVehLeft="0" nVehSeen="0" meanSpeed="-1.00" meanTimeLoss="-1.00" meanOccupancy="0.00" maxOccupancy="0.00" meanMaxJamLengthInVehicles="0.00" meanMaxJamLengthInMeters="0.00" maxJamLengthInVehicles="0" maxJamLengthInMeters="0.00" jamLengthInVehiclesSum="0" jamLengthInMetersSum="0.00" meanHaltingDuration="0.00" maxHaltingDuration="0.00" haltingDurationSum="0.00" meanIntervalHaltingDuration="0.00" maxIntervalHaltingDuration="0.00" intervalHaltingDurationSum="0.00" startedHalts="0.00" meanVehicleNumber="0.00" maxVehicleNumber="0" />
   <interval begin="3000.00" end="3120.00" id="e2_east_0" sampledSeconds="23.09" nVehEntered="15" nVehLeft="16" nVehSeen="16" meanSpeed="17.05" meanTimeLoss="0.10" meanOccupancy="3.81" maxOccupancy="25.00" meanMaxJamLengthInVehicles="0.00" meanMaxJamLengthInMeters="0.00" maxJamLengthInVehicles="0" maxJamLengthInMeters="0.00" jamLengthInVehiclesSum="0" jamLengthInMetersSum="0.00" meanHaltingDuration="0.00" maxHaltingDuration="0.00" haltingDurationSum="0.00" meanIntervalHaltingDuration="0.00" maxIntervalHaltingDuration="0.00" intervalHaltingDurationSum="0.00" startedHalts="0.00" meanVehicleNumber="0.32" maxVehicleNumber="1" />
   <interval begin="3000.00" end="3120.00" id="e2_east_1" sampledSeconds="22.03" nVehEntered="13" nVehLeft="14" nVehSeen="14" meanSpeed="14.58" meanTimeLoss="0.38" meanOccupancy="3.21" maxOccupancy="25.00" meanMaxJamLengthInVehicles="0.00" meanMaxJamLengthInMeters="0.00" maxJamLengthInVehicles="0" maxJamLengthInMeters="0.00" jamLengthInVehiclesSum="0" jamLengthInMetersSum="0.00" meanHaltingDuration="1.00" maxHaltingDuration="1.00" haltingDurationSum="1.00" meanIntervalHaltingDuration="1.00" maxIntervalHaltingDuration="1.00" intervalHaltingDurationSum="1.00" startedHalts="1.00" meanVehicleNumber="0.30" maxVehicleNumber="1" />
   <interval begin="3000.00" end="3120.00" id="e2_east_2" sampledSeconds="93.62" nVehEntered="40" nVehLeft="43" nVehSeen="43" meanSpeed="10.95" meanTimeLoss="0.96" meanOccupancy="15.54" maxOccupancy="59.59" meanMaxJamLengthInVehicles="0.01" meanMaxJamLengthInMeters="0.04" maxJamLengthInVehicles="1" maxJamLengthInMeters="5.00" jamLengthInVehiclesSum="1" jamLengthInMetersSum="5.00" meanHaltingDuration="1.17" maxHaltingDuration="2.00" haltingDurationSum="7.00" meanIntervalHaltingDuration="1.00" maxIntervalHaltingDuration="2.00" intervalHaltingDurationSum="6.00" startedHalts="5.00" meanVehicleNumber="1.12" maxVehicleNumber="3" />
   <interval begin="3000.00" end="3120.00" id="e2_east_3" sampledSeconds="0.00" nVehEntered="0" nVehLeft="0" nVehSeen="0" meanSpeed="-1.00" meanTimeLoss="-1.00" meanOccupancy="0.00" maxOccupancy="0.00" meanMaxJamLengthInVehicles="0.00" meanMaxJamLengthInMeters="0.00" maxJamLengthInVehicles="0" maxJamLengthInMeters="0.00" jamLengthInVehiclesSum="0" jamLengthInMetersSum="0.00" meanHaltingDuration="0.00" maxHaltingDuration="0.00" haltingDurationSum="0.00" meanIntervalHaltingDuration="0.00" maxIntervalHaltingDuration="0.00" intervalHaltingDurationSum="0.00" startedHalts="0.00" meanVehicleNumber="0.00" maxVehicleNumber="0" />
   <interval begin="3000.00" end="3120.00" id="e2_east_4" sampledSeconds="0.00" nVehEntered="0" nVehLeft="0" nVehSeen="0" meanSpeed="-1.00" meanTimeLoss="-1.00" meanOccupancy="0.00" maxOccupancy="0.00" meanMaxJamLengthInVehicles="0.00" meanMaxJamLengthInMeters="0.00" maxJamLengthInVehicles="0" maxJamLengthInMeters="0.00" jamLengthInVehiclesSum="0" jamLengthInMetersSum="0.00" meanHaltingDuration="0.00" maxHaltingDuration="0.00" haltingDurationSum="0.00" meanIntervalHaltingDuration="0.00" maxIntervalHaltingDuration="0.00" intervalHaltingDurationSum="0.00" startedHalts="0.00" meanVehicleNumber="0.00" maxVehicleNumber="0" />
   <interval begin="3120.00" end="3240.00" id="e2_east_0" sampledSeconds="28.92" nVehEntered="20" nVehLeft="20" nVehSeen="20" meanSpeed="15.74" meanTimeLoss="0.18" meanOccupancy="5.20" maxOccupancy="25.00" meanMaxJamLengthInVehicles="0.00" meanMaxJamLengthInMeters="0.00" maxJamLengthInVehicles="0" maxJamLengthInMeters="0.00" jamLengthInVehiclesSum="0" jamLengthInMetersSum="0.00" meanHaltingDuration="0.00" maxHaltingDuration="0.00" haltingDurationSum="0.00" meanIntervalHaltingDuration="0.00" maxIntervalHaltingDuration="0.00" intervalHaltingDurationSum="0.00" startedHalts="0.00" meanVehicleNumber="0.42" maxVehicleNumber="2" />
   <interval begin="3120.00" end="3240.00" id="e2_east_1" sampledSeconds="25.60" nVehEntered="15" nVehLeft="14" nVehSeen="15" meanSpeed="12.40" meanTimeLoss="0.60" meanOccupancy="3.67" maxOccupancy="25.00" meanMaxJamLengthInVehicles="0.00" meanMaxJamLengthInMeters="0.00" maxJamLengthInVehicles="0" maxJamLengthInMeters="0.00" jamLengthInVehiclesSum="0" jamLengthInMetersSum="0.00" meanHaltingDuration="0.00" maxHaltingDuration="0.00" haltingDurationSum="0.00" meanIntervalHaltingDuration="0.00" maxIntervalHaltingDuration="0.00" intervalHaltingDurationSum="0.00" startedHalts="0.00" meanVehicleNumber="0.32" maxVehicleNumber="1" />
   <interval begin="3120.00" end="3240.00" id="e2_east_2" sampledSeconds="103.86" nVehEntered="36" nVehLeft="36" nVehSeen="36" meanSpeed="8.55" meanTimeLoss="1.62" meanOccupancy="18.30" maxOccupancy="70.24" meanMaxJamLengthInVehicles="0.17" meanMaxJamLengthInMeters="0.94" maxJamLengthInVehicles="3" maxJamLengthInMeters="19.12" jamLengthInVehiclesSum="21" jamLengthInMetersSum="112.48" meanHaltingDuration="8.00" maxHaltingDuration="14.00" haltingDurationSum="24.00" meanIntervalHaltingDuration="8.00" maxIntervalHaltingDuration="14.00" intervalHaltingDurationSum="24.00" startedHalts="4.00" meanVehicleNumber="1.16" maxVehicleNumber="3" />
   <interval begin="3120.00" end="3240.00" id="e2_east_3" sampledSeconds="0.00" nVehEntered="0" nVehLeft="0" nVehSeen="0" meanSpeed="-1.00" meanTimeLoss="-1.00" meanOccupancy="0.00" maxOccupancy="0.00" meanMaxJamLengthInVehicles="0.00" meanMaxJamLengthInMeters="0.00" maxJamLengthInVehicles="0" maxJamLengthInMeters="0.00" jamLengthInVehiclesSum="0" jamLengthInMetersSum="0.00" meanHaltingDuration="0.00" maxHaltingDuration="0.00" haltingDurationSum="0.00" meanIntervalHaltingDuration="0.00" maxIntervalHaltingDuration="0.00" intervalHaltingDurationSum="0.00" startedHalts="0.00" meanVehicleNumber="0.00" maxVehicleNumber="0" />
   <interval begin="3120.00" end="3240.00" id="e2_east_4" sampledSeconds="0.00" nVehEntered="0" nVehLeft="0" nVehSeen="0" meanSpeed="-1.00" meanTimeLoss="-1.00" meanOccupancy="0.00" maxOccupancy="0.00" meanMaxJamLengthInVehicles="0.00" meanMaxJamLengthInMeters="0.00" maxJamLengthInVehicles="0" maxJamLengthInMeters="0.00" jamLengthInVehiclesSum="0" jamLengthInMetersSum="0.00" meanHaltingDuration="0.00" maxHaltingDuration="0.00" haltingDurationSum="0.00" meanIntervalHaltingDuration="0.00" maxIntervalHaltingDuration="0.00" intervalHaltingDurationSum="0.00" startedHalts="0.00" meanVehicleNumber="0.00" maxVehicleNumber="0" />
   <interval begin="3240.00" end="3360.00" id="e2_east_0" sampledSeconds="82.21" nVehEntered="19" nVehLeft="18" nVehSeen="19" meanSpeed="5.19" meanTimeLoss="3.16" meanOccupancy="14.81" maxOccupancy="71.97" meanMaxJamLengthInVehicles="0.27" meanMaxJamLengthInMeters="1.59" maxJamLengthInVehicles="3" maxJamLengthInMeters="19.44" jamLengthInVehiclesSum="32" jamLengthInMetersSum="190.84" meanHaltingDuration="9.00" maxHaltingDuration="15.00" haltingDurationSum="36.00" meanIntervalHaltingDuration="9.00" maxIntervalHaltingDuration="15.00" intervalHaltingDurationSum="36.00" startedHalts="4.00" meanVehicleNumber="0.82" maxVehicleNumber="3" />
   <interval begin="3240.00" end="3360.00" id="e2_east_1" sampledSeconds="101.95" nVehEntered="18" nVehLeft="19" nVehSeen="19" meanSpeed="4.13" meanTimeLoss="4.21" meanOccupancy="17.86" maxOccupancy="72.16" meanMaxJamLengthInVehicles="0.35" meanMaxJamLengthInMeters="2.14" maxJamLengthInVehicles="3" maxJamLengthInMeters="19.50" jamLengthInVehiclesSum="42" jamLengthInMetersSum="256.20" meanHaltingDuration="9.20" maxHaltingDuration="17.00" haltingDurationSum="46.00" meanIntervalHaltingDuration="9.20" maxIntervalHaltingDuration="17.00" intervalHaltingDurationSum="46.00" startedHalts="6.00" meanVehicleNumber="0.98" maxVehicleNumber="3" />
   <interval begin="3240.00" end="3360.00" id="e2_east_2" sampledSeconds="163.64" nVehEntered="34" nVehLeft="34" nVehSeen="34" meanSpeed="4.88" meanTimeLoss="3.60" meanOccupancy="30.24" maxOccupancy="72.16" meanMaxJamLengthInVehicles="0.63" meanMaxJamLengthInMeters="3.89" maxJamLengthInVehicles="3" maxJamLengthInMeters="19.45" jamLengthInVehiclesSum="76" jamLengthInMetersSum="466.49" meanHaltingDuration="18.75" maxHaltingDuration="33.00" haltingDurationSum="75.00" meanIntervalHaltingDuration="18.75" maxIntervalHaltingDuration="33.00" intervalHaltingDurationSum="75.00" startedHalts="7.00" meanVehicleNumber="1.63" maxVehicleNumber="3" />
   <interval begin="3240.00" end="3360.00" id="e2_east_3" sampledSeconds="0.00" nVehEntered="0" nVehLeft="0" nVehSeen="0" meanSpeed="-1.00" meanTimeLoss="-1.00" meanOccupancy="0.00" maxOccupancy="0.00" meanMaxJamLengthInVehicles="0.00" meanMaxJamLengthInMeters="0.00" maxJamLengthInVehicles="0" maxJamLengthInMeters="0.00" jamLengthInVehiclesSum="0" jamLengthInMetersSum="0.00" meanHaltingDuration="0.00" maxHaltingDuration="0.00" haltingDurationSum="0.00" meanIntervalHaltingDuration="0.00" maxIntervalHaltingDuration="0.00" intervalHaltingDurationSum="0.00" startedHalts="0.00" meanVehicleNumber="0.00" maxVehicleNumber="0" />
   <interval begin="3240.00" end="3360.00" id="e2_east_4" sampledSeconds="0.00" nVehEntered="0" nVehLeft="0" nVehSeen="0" meanSpeed="-1.00" meanTimeLoss="-1.00" meanOccupancy="0.00" maxOccupancy="0.00" meanMaxJamLengthInVehicles="0.00" meanMaxJamLengthInMeters="0.00" maxJamLengthInVehicles="0" maxJamLengthInMeters="0.00" jamLengthInVehiclesSum="0" jamLengthInMetersSum="0.00" meanHaltingDuration="0.00" maxHaltingDuration="0.00" haltingDurationSum="0.00" meanIntervalHaltingDuration="0.00" maxIntervalHaltingDuration="0.00" intervalHaltingDurationSum="0.00" startedHalts="0.00" meanVehicleNumber="0.00" maxVehicleNumber="0" />
   <interval begin="3360.00" end="3480.00" id="e2_east_0" sampledSeconds="100.98" nVehEntered="18" nVehLeft="19" nVehSeen="19" meanSpeed="4.01" meanTimeLoss="4.16" meanOccupancy="18.58" maxOccupancy="72.16" meanMaxJamLengthInVehicles="0.43" meanMaxJamLengthInMeters="2.63" maxJamLengthInVehicles="3" maxJamLengthInMeters="19.57" jamLengthInVehiclesSum="52" jamLengthInMetersSum="315.13" meanHaltingDuration="14.00" maxHaltingDuration="24.00" haltingDurationSum="56.00" meanIntervalHaltingDuration="14.00" maxIntervalHaltingDuration="24.00" intervalHaltingDurationSum="56.00" startedHalts="4.00" meanVehicleNumber="0.98" maxVehicleNumber="3" />
   <interval begin="3360.00" end="3480.00" id="e2_east_1" sampledSeconds="107.05" nVehEntered="19" nVehLeft="19" nVehSeen="19" meanSpeed="3.34" meanTimeLoss="4.67" meanOccupancy="18.75" maxOccupancy="72.16" meanMaxJamLengthInVehicles="0.47" meanMaxJamLengthInMeters="2.98" maxJamLengthInVehicles="3" maxJamLengthInMeters="19.47" jamLengthInVehiclesSum="57" jamLengthInMetersSum="357.75" meanHaltingDuration="15.25" maxHaltingDuration="23.00" haltingDurationSum="61.00" meanIntervalHaltingDuration="15.25" maxIntervalHaltingDuration="23.00" intervalHaltingDurationSum="61.00" startedHalts="4.00" meanVehicleNumber="1.02" maxVehicleNumber="3" />
   <interval begin="3360.00" end="3480.00" id="e2_east_2" sampledSeconds="178.75" nVehEntered="35" nVehLeft="34" nVehSeen="35" meanSpeed="4.74" meanTimeLoss="3.87" meanOccupancy="32.69" maxOccupancy="72.16" meanMaxJamLengthInVehicles="0.62" meanMaxJamLengthInMeters="3.85" maxJamLengthInVehicles="3" maxJamLengthInMeters="19.44" jamLengthInVehiclesSum="74" jamLengthInMetersSum="461.95" meanHaltingDuration="19.25" maxHaltingDuration="30.00" haltingDurationSum="77.00" meanIntervalHaltingDuration="19.25" maxIntervalHaltingDuration="30.00" intervalHaltingDurationSum="77.00" startedHalts="6.00" meanVehicleNumber="1.77" maxVehicleNumber="3" />
   <interval begin="3360.00" end="3480.00" id="e2_east_3" sampledSeconds="1.38" nVehEntered="1" nVehLeft="1" nVehSeen="1" meanSpeed="18.16" meanTimeLoss="0.01" meanOccupancy="0.21" maxOccupancy="25.00" meanMaxJamLengthInVehicles="0.00" meanMaxJamLengthInMeters="0.00" maxJamLengthInVehicles="0" maxJamLengthInMeters="0.00" jamLengthInVehiclesSum="0" jamLengthInMetersSum="0.00" meanHaltingDuration="0.00" maxHaltingDuration="0.00" haltingDurationSum="0.00" meanIntervalHaltingDuration="0.00" maxIntervalHaltingDuration="0.00" intervalHaltingDurationSum="0.00" startedHalts="0.00" meanVehicleNumber="0.02" maxVehicleNumber="1" />
   <interval begin="3360.00" end="3480.00" id="e2_east_4" sampledSeconds="0.00" nVehEntered="0" nVehLeft="0" nVehSeen="0" meanSpeed="-1.00" meanTimeLoss="-1.00" meanOccupancy="0.00" maxOccupancy="0.00" meanMaxJamLengthInVehicles="0.00" meanMaxJamLengthInMeters="0.00" maxJamLengthInVehicles="0" maxJamLengthInMeters="0.00" jamLengthInVehiclesSum="0" jamLengthInMetersSum="0.00" meanHaltingDuration="0.00" maxHaltingDuration="0.00" haltingDurationSum="0.00" meanIntervalHaltingDuration="0.00" maxIntervalHaltingDuration="0.00" intervalHaltingDurationSum="0.00" startedHalts="0.00" meanVehicleNumber="0.00" maxVehicleNumber="0" />
   <interval begin="3480.00" end="3600.00" id="e2_east_0" sampledSeconds="19.31" nVehEntered="13" nVehLeft="13" nVehSeen="13" meanSpeed="16.83" meanTimeLoss="0.12" meanOccupancy="2.94" maxOccupancy="25.00" meanMaxJamLengthInVehicles="0.00" meanMaxJamLengthInMeters="0.00" maxJamLengthInVehicles="0" maxJamLengthInMeters="0.00" jamLengthInVehiclesSum="0" jamLengthInMetersSum="0.00" meanHaltingDuration="0.00" maxHaltingDuration="0.00" haltingDurationSum="0.00" meanIntervalHaltingDuration="0.00" maxIntervalHaltingDuration="0.00" intervalHaltingDurationSum="0.00" startedHalts="0.00" meanVehicleNumber="0.26" maxVehicleNumber="1" />
   <interval begin="3480.00" end="3600.00" id="e2_east_1" sampledSeconds="27.02" nVehEntered="14" nVehLeft="13" nVehSeen="14" meanSpeed="11.08" meanTimeLoss="0.80" meanOccupancy="4.59" maxOccupancy="25.00" meanMaxJamLengthInVehicles="0.00" meanMaxJamLengthInMeters="0.00" maxJamLengthInVehicles="0" maxJamLengthInMeters="0.00" jamLengthInVehiclesSum="0" jamLengthInMetersSum="0.00" meanHaltingDuration="0.00" maxHaltingDuration="0.00" haltingDurationSum="0.00" meanIntervalHaltingDuration="0.00" maxIntervalHaltingDuration="0.00" intervalHaltingDurationSum="0.00" startedHalts="0.00" meanVehicleNumber="0.33" maxVehicleNumber="2" />
   <interval begin="3480.00" end="3600.00" id="e2_east_2" sampledSeconds="100.90" nVehEntered="44" nVehLeft="43" nVehSeen="45" meanSpeed="10.22" meanTimeLoss="1.06" meanOccupancy="17.71" maxOccupancy="71.80" meanMaxJamLengthInVehicles="0.08" meanMaxJamLengthInMeters="0.45" maxJamLengthInVehicles="2" maxJamLengthInMeters="11.94" jamLengthInVehiclesSum="10" jamLengthInMetersSum="53.60" meanHaltingDuration="6.00" maxHaltingDuration="8.00" haltingDurationSum="12.00" meanIntervalHaltingDuration="6.00" maxIntervalHaltingDuration="8.00" intervalHaltingDurationSum="12.00" startedHalts="4.00" meanVehicleNumber="1.16" maxVehicleNumber="3" />
   <interval begin="3480.00" end="3600.00" id="e2_east_3" sampledSeconds="0.00" nVehEntered="0" nVehLeft="0" nVehSeen="0" meanSpeed="-1.00" meanTimeLoss="-1.00" meanOccupancy="0.00" maxOccupancy="0.00" meanMaxJamLengthInVehicles="0.00" meanMaxJamLengthInMeters="0.00" maxJamLengthInVehicles="0" maxJamLengthInMeters="0.00" jamLengthInVehiclesSum="0" jamLengthInMetersSum="0.00" meanHaltingDuration="0.00" maxHaltingDuration="0.00" haltingDurationSum="0.00" meanIntervalHaltingDuration="0.00" maxIntervalHaltingDuration="0.00" intervalHaltingDurationSum="0.00" startedHalts="0.00" meanVehicleNumber="0.00" maxVehicleNumber="0" />
   <interval begin="3480.00" end="3600.00" id="e2_east_4" sampledSeconds="0.00" nVehEntered="0" nVehLeft="0" nVehSeen="0" meanSpeed="-1.00" meanTimeLoss="-1.00" meanOccupancy="0.00" maxOccupancy="0.00" meanMaxJamLengthInVehicles="0.00" meanMaxJamLengthInMeters="0.00" maxJamLengthInVehicles="0" maxJamLengthInMeters="0.00" jamLengthInVehiclesSum="0" jamLengthInMetersSum="0.00" meanHaltingDuration="0.00" maxHaltingDuration="0.00" haltingDurationSum="0.00" meanIntervalHaltingDuration="0.00" maxIntervalHaltingDuration="0.00" intervalHaltingDurationSum="0.00" startedHalts="0.00" meanVehicleNumber="0.00" maxVehicleNumber="0" />
</detector>
